{
  "org-indent": {
    "fg": "#f7f3ee"
  },
  "org-superstar-first": {
    "fg": "#957f5f"
  },
  "org-superstar-ordered-item": {
    "fg": "#605a52",
    "bg": "#f7f3ee"
  },
  "org-superstar-item": {
    "fg": "#605a52",
    "bg": "#f7f3ee"
  },
  "org-superstar-leading": {
    "fg": "gray",
    "bg": "#f7f3ee"
  },
  "eww-valid-certificate": {
    "fg": "#7382a0"
  },
  "eww-invalid-certificate": {
    "fg": "#955f5f"
  },
  "eww-form-textarea": {
    "fg": "#605a52",
    "bg": "#f7f3ee"
  },
  "eww-form-text": {
    "fg": "#605a52",
    "bg": "#f7f3ee"
  },
  "eww-form-select": {
    "fg": "#605a52",
    "bg": "#f1ece4"
  },
  "eww-form-checkbox": {
    "fg": "#605a52",
    "bg": "#f1ece4"
  },
  "eww-form-file": {
    "fg": "#605a52",
    "bg": "#f1ece4"
  },
  "eww-form-submit": {
    "fg": "#605a52",
    "bg": "#dcd3c6"
  },
  "gnus-header-content": {
    "fg": "#9c739c"
  },
  "gnus-header-name": {
    "fg": "#81895d"
  },
  "gnus-header-newsgroups": {
    "fg": "#9c739c"
  },
  "gnus-header-subject": {
    "fg": "#7382a0"
  },
  "gnus-header-from": {
    "fg": "#9c739c"
  },
  "gnus-signature": {
    "fg": "#957f5f"
  },
  "gnus-emphasis-highlight-words": {
    "fg": "yellow",
    "bg": "black"
  },
  "mm-uu-extract": {
    "fg": "#62605d",
    "bg": "#d4cdc3"
  },
  "shr-mark": {
    "fg": "black",
    "bg": "yellow"
  },
  "shr-h6": {
    "fg": "#605a52",
    "bg": "#f7f3ee"
  },
  "shr-h5": {
    "fg": "#605a52",
    "bg": "#f7f3ee"
  },
  "shr-h4": {
    "fg": "#605a52",
    "bg": "#f7f3ee"
  },
  "shr-selected-link": {
    "fg": "#7382a0",
    "bg": "red"
  },
  "shr-link": {
    "fg": "#7382a0"
  },
  "gnus-splash": {
    "fg": "#888888"
  },
  "gnus-summary-low-read": {
    "fg": "#4c4841"
  },
  "gnus-summary-high-read": {
    "fg": "#7f7b74"
  },
  "gnus-summary-normal-read": {
    "fg": "#605a52"
  },
  "gnus-summary-low-unread": {
    "fg": "#676d4a"
  },
  "gnus-summary-high-unread": {
    "fg": "#9aa07d"
  },
  "gnus-summary-normal-unread": {
    "fg": "#81895d"
  },
  "gnus-summary-low-undownloaded": {
    "fg": "cyan4"
  },
  "gnus-summary-high-undownloaded": {
    "fg": "cyan4"
  },
  "gnus-summary-normal-undownloaded": {
    "fg": "cyan4"
  },
  "gnus-summary-low-ancient": {
    "fg": "#4c4841"
  },
  "gnus-summary-high-ancient": {
    "fg": "#7f7b74"
  },
  "gnus-summary-normal-ancient": {
    "fg": "#605a52"
  },
  "gnus-summary-low-ticked": {
    "fg": "#7c5c7c"
  },
  "gnus-summary-high-ticked": {
    "fg": "#af8faf"
  },
  "gnus-summary-normal-ticked": {
    "fg": "#9c739c"
  },
  "gnus-summary-cancelled": {
    "fg": "#955f5f"
  },
  "gnus-summary-selected": {
    "fg": "#7382a0"
  },
  "gnus-group-mail-low": {
    "fg": "#605a52"
  },
  "gnus-group-mail-low-empty": {
    "fg": "#605a52"
  },
  "gnus-group-mail-3": {
    "fg": "#605a52"
  },
  "gnus-group-mail-3-empty": {
    "fg": "#605a52"
  },
  "gnus-group-mail-2": {
    "fg": "#605a52"
  },
  "gnus-group-mail-2-empty": {
    "fg": "#605a52"
  },
  "gnus-group-mail-1": {
    "fg": "#605a52"
  },
  "gnus-group-mail-1-empty": {
    "fg": "#605a52"
  },
  "gnus-group-news-low": {
    "fg": "#605a52"
  },
  "gnus-group-news-low-empty": {
    "fg": "#605a52"
  },
  "gnus-group-news-6": {
    "fg": "#605a52"
  },
  "gnus-group-news-6-empty": {
    "fg": "#605a52"
  },
  "gnus-group-news-5": {
    "fg": "#605a52"
  },
  "gnus-group-news-5-empty": {
    "fg": "#605a52"
  },
  "gnus-group-news-4": {
    "fg": "#605a52"
  },
  "gnus-group-news-4-empty": {
    "fg": "#605a52"
  },
  "gnus-group-news-3": {
    "fg": "#605a52"
  },
  "gnus-group-news-3-empty": {
    "fg": "#605a52"
  },
  "gnus-group-news-2": {
    "fg": "#605a52"
  },
  "gnus-group-news-2-empty": {
    "fg": "#605a52"
  },
  "gnus-group-news-1": {
    "fg": "#605a52"
  },
  "gnus-group-news-1-empty": {
    "fg": "#605a52"
  },
  "doc-view-svg-face": {
    "fg": "black",
    "bg": "white"
  },
  "org-habit-overdue-future-face": {
    "bg": "#d5c1bc"
  },
  "org-habit-overdue-face": {
    "bg": "#c3a5a1"
  },
  "org-habit-alert-future-face": {
    "bg": "#d5cbbc"
  },
  "org-habit-alert-face": {
    "bg": "#c3b5a1"
  },
  "org-habit-ready-future-face": {
    "bg": "#cbcccf"
  },
  "org-habit-ready-face": {
    "bg": "#b2b7c2"
  },
  "org-habit-clear-future-face": {
    "bg": "#b9a992"
  },
  "org-habit-clear-face": {
    "bg": "#93836c"
  },
  "restclient-request-hook-args-face": {
    "fg": "#525643",
    "bg": "#e2e9c1"
  },
  "restclient-request-hook-name-face": {
    "fg": "#605a52"
  },
  "restclient-request-hook-face": {
    "fg": "#605a52",
    "bg": "#f7f3ee"
  },
  "restclient-header-value-face": {
    "fg": "#525643",
    "bg": "#e2e9c1"
  },
  "restclient-header-name-face": {
    "fg": "#4c5361",
    "bg": "#dde4f2"
  },
  "restclient-file-upload-face": {
    "fg": "#9d8f7c"
  },
  "restclient-url-face": {
    "fg": "#605a52"
  },
  "restclient-method-face": {
    "fg": "#614c61",
    "bg": "#f1ddf1"
  },
  "restclient-variable-usage-face": {
    "fg": "#605a52",
    "bg": "#f7f3ee"
  },
  "restclient-variable-multiline-face": {
    "fg": "#9d8f7c"
  },
  "restclient-variable-elisp-face": {
    "fg": "#605a52"
  },
  "restclient-variable-string-face": {
    "fg": "#525643",
    "bg": "#e2e9c1"
  },
  "restclient-variable-name-face": {
    "fg": "#605a52",
    "bg": "#f7f3ee"
  },
  "sh-escaped-newline": {
    "fg": "#525643",
    "bg": "#e2e9c1"
  },
  "sh-quoted-exec": {
    "fg": "#605a52",
    "bg": "#f7f3ee"
  },
  "sh-heredoc": {
    "fg": "#525643",
    "bg": "#e2e9c1"
  },
  "treesit-explorer-anonymous-node": {
    "fg": "#605a52"
  },
  "org-mode-line-clock-overrun": {
    "bg": "red"
  },
  "org-mode-line-clock": {
    "bg": "#e4ddd2"
  },
  "org-tag-group": {
    "fg": "#9d8f7c"
  },
  "org-macro": {
    "fg": "#1b2229"
  },
  "org-latex-and-related": {
    "fg": "#1b2229"
  },
  "org-agenda-calendar-sexp": {
    "fg": "#605a52",
    "bg": "#f7f3ee"
  },
  "org-agenda-calendar-event": {
    "fg": "#605a52",
    "bg": "#f7f3ee"
  },
  "org-agenda-calendar-daterange": {
    "fg": "#605a52",
    "bg": "#f7f3ee"
  },
  "org-agenda-diary": {
    "fg": "#605a52",
    "bg": "#f7f3ee"
  },
  "org-agenda-current-time": {
    "fg": "#b9a992"
  },
  "org-time-grid": {
    "fg": "#b9a992"
  },
  "org-agenda-filter-regexp": {
    "bg": "#e4ddd2"
  },
  "org-agenda-filter-effort": {
    "bg": "#e4ddd2"
  },
  "org-agenda-filter-category": {
    "bg": "#e4ddd2"
  },
  "org-agenda-filter-tags": {
    "bg": "#e4ddd2"
  },
  "org-agenda-restriction-lock": {
    "bg": "#eeeeee"
  },
  "org-upcoming-distant-deadline": {
    "fg": "#aba6a0"
  },
  "org-upcoming-deadline": {
    "fg": "#7e7871"
  },
  "org-imminent-deadline": {
    "fg": "#957f5f"
  },
  "org-scheduled-previously": {
    "fg": "#1b2229"
  },
  "org-agenda-dimmed-todo-face": {
    "fg": "#b9a992"
  },
  "org-scheduled-today": {
    "fg": "#1c1f24"
  },
  "org-scheduled": {
    "fg": "#605a52"
  },
  "org-agenda-date-weekend": {
    "fg": "#5d455d"
  },
  "org-agenda-clocking": {
    "bg": "#dcdcde"
  },
  "org-agenda-date-weekend-today": {
    "fg": "#c3abc3"
  },
  "org-agenda-date-today": {
    "fg": "#c3abc3"
  },
  "org-agenda-date": {
    "fg": "#9c739c"
  },
  "org-agenda-structure-filter": {
    "fg": "#957f5f"
  },
  "org-agenda-structure-secondary": {
    "fg": "#605a52"
  },
  "org-agenda-structure": {
    "fg": "#605a52"
  },
  "org-clock-overlay": {
    "fg": "black",
    "bg": "LightGray"
  },
  "org-verse": {
    "fg": "#5b5143",
    "bg": "#f7e0c3"
  },
  "org-quote": {
    "fg": "#5b5143",
    "bg": "#f7e0c3"
  },
  "org-verbatim": {
    "fg": "#81895d"
  },
  "org-inline-src-block": {
    "fg": "#5b5143",
    "bg": "#f7e0c3"
  },
  "org-block-end-line": {
    "fg": "#5b5143",
    "bg": "#f7e0c3"
  },
  "org-block-begin-line": {
    "fg": "#5b5143",
    "bg": "#f7e0c3"
  },
  "org-block": {
    "fg": "#5b5143",
    "bg": "#f7e0c3"
  },
  "org-document-info-keyword": {
    "fg": "#605a52"
  },
  "org-document-info": {
    "fg": "#9c739c"
  },
  "org-document-title": {
    "fg": "#9c739c"
  },
  "org-meta-line": {
    "fg": "#9d8f7c"
  },
  "org-code": {
    "fg": "#957f5f",
    "bg": "#f7e0c3"
  },
  "org-formula": {
    "fg": "#5f8c7d"
  },
  "org-table-header": {
    "fg": "Black",
    "bg": "LightGray"
  },
  "org-table-row": {
    "fg": "#9c739c"
  },
  "org-table": {
    "fg": "#9c739c"
  },
  "org-checkbox-statistics-done": {
    "fg": "#605a52"
  },
  "org-checkbox-statistics-todo": {
    "fg": "#81895d"
  },
  "org-checkbox": {
    "fg": "#81895d"
  },
  "org-priority": {
    "fg": "#955f5f"
  },
  "org-headline-done": {
    "fg": "#605a52"
  },
  "org-headline-todo": {
    "fg": "Red4"
  },
  "org-agenda-done": {
    "fg": "#605a52"
  },
  "org-done": {
    "fg": "#605a52"
  },
  "org-todo": {
    "fg": "#81895d"
  },
  "org-list-dt": {
    "fg": "#7382a0"
  },
  "org-tag": {
    "fg": "#9d8f7c"
  },
  "org-sexp-date": {
    "fg": "#605a52"
  },
  "org-date-selected": {
    "fg": "Red1"
  },
  "org-date": {
    "fg": "#957f5f"
  },
  "org-ellipsis": {
    "fg": "#955f5f",
    "bg": "#f7f3ee"
  },
  "org-footnote": {
    "fg": "#957f5f"
  },
  "org-link": {
    "fg": "#7382a0"
  },
  "org-cite-key": {
    "fg": "#5f786b"
  },
  "org-cite": {
    "fg": "#5f8778"
  },
  "org-archived": {
    "fg": "#9d8f7c"
  },
  "org-warning": {
    "fg": "#957f5f"
  },
  "org-agenda-column-dateline": {
    "bg": "grey90"
  },
  "org-column-title": {
    "bg": "grey90"
  },
  "org-column": {
    "bg": "grey90"
  },
  "org-property-value": {
    "fg": "#9d8f7c"
  },
  "org-drawer": {
    "fg": "#b9a992"
  },
  "org-special-keyword": {
    "fg": "#9d8f7c"
  },
  "org-level-8": {
    "fg": "#e3e6ec"
  },
  "org-level-7": {
    "fg": "#cdb9cd"
  },
  "org-level-6": {
    "fg": "#b9c0cf"
  },
  "org-level-5": {
    "fg": "#b496b4"
  },
  "org-level-4": {
    "fg": "#96a1b7"
  },
  "org-level-3": {
    "fg": "#9c739c"
  },
  "org-level-2": {
    "fg": "#957f5f"
  },
  "org-level-1": {
    "fg": "#955f5f"
  },
  "org-dispatcher-highlight": {
    "fg": "DarkBlue",
    "bg": "SlateGray1"
  },
  "org-hide": {
    "fg": "#f7f3ee"
  },
  "outline-8": {
    "fg": "#e3e6ec"
  },
  "outline-7": {
    "fg": "#cdb9cd"
  },
  "outline-6": {
    "fg": "#b9c0cf"
  },
  "outline-5": {
    "fg": "#b496b4"
  },
  "outline-4": {
    "fg": "#96a1b7"
  },
  "outline-3": {
    "fg": "#9c739c"
  },
  "outline-2": {
    "fg": "#957f5f"
  },
  "outline-1": {
    "fg": "#955f5f"
  },
  "calendar-month-header": {
    "fg": "#605a52"
  },
  "calendar-weekend-header": {
    "fg": "#b9a992"
  },
  "calendar-weekday-header": {
    "fg": "#465953",
    "bg": "#d2ebe3"
  },
  "holiday": {
    "bg": "pink"
  },
  "diary": {
    "fg": "red1"
  },
  "whitespace-space-after-tab": {
    "fg": "firebrick",
    "bg": "yellow"
  },
  "whitespace-empty": {
    "bg": "#b9a992"
  },
  "whitespace-missing-newline-at-eof": {
    "fg": "black",
    "bg": "#d0d040"
  },
  "whitespace-big-indent": {
    "fg": "firebrick",
    "bg": "red"
  },
  "whitespace-indentation": {
    "fg": "#93836c"
  },
  "whitespace-space-before-tab": {
    "fg": "firebrick",
    "bg": "DarkOrange"
  },
  "whitespace-line": {
    "fg": "#955f5f",
    "bg": "#f1ece4"
  },
  "whitespace-trailing": {
    "bg": "#955f5f"
  },
  "whitespace-newline": {
    "fg": "#93836c"
  },
  "whitespace-tab": {
    "fg": "#93836c",
    "bg": "#f1ece4"
  },
  "whitespace-hspace": {
    "fg": "lightgray",
    "bg": "LemonChiffon3"
  },
  "whitespace-space": {
    "fg": "#93836c"
  },
  "helm-swoop-line-number-face": {
    "fg": "#999999"
  },
  "helm-swoop-target-word-face": {
    "fg": "#81895d"
  },
  "helm-swoop-target-line-block-face": {
    "fg": "#957f5f"
  },
  "helm-swoop-target-line-face": {
    "fg": "#7382a0"
  },
  "helm-M-x-short-doc": {
    "fg": "DimGray"
  },
  "helm-command-debug-active": {
    "fg": "#5b4343",
    "bg": "#f6cfcb"
  },
  "helm-command-minor-active-mode": {
    "fg": "#605a52",
    "bg": "#f7f3ee"
  },
  "helm-command-major-active-mode": {
    "fg": "#605a52"
  },
  "helm-M-x-key": {
    "fg": "orange"
  },
  "helm-lisp-completion-info": {
    "fg": "red"
  },
  "helm-lisp-show-completion": {
    "bg": "DarkSlateGray"
  },
  "edebug-disabled-breakpoint": {
    "bg": "#ddffdd"
  },
  "edebug-enabled-breakpoint": {
    "fg": "#f1ece4",
    "bg": "#7382a0"
  },
  "helm-descbinds-binding": {
    "fg": "#5b4343",
    "bg": "#f6cfcb"
  },
  "helm-completions-key-binding": {
    "fg": "#465953",
    "bg": "#d2ebe3"
  },
  "helm-completions-annotations": {
    "fg": "#4c5361",
    "bg": "#dde4f2"
  },
  "helm-completions-detailed": {
    "fg": "#5b4343",
    "bg": "#f6cfcb"
  },
  "helm-completion-invalid": {
    "fg": "#4c5361",
    "bg": "#dde4f2"
  },
  "helm-time-zone-home": {
    "fg": "red"
  },
  "helm-time-zone-current": {
    "fg": "green"
  },
  "helm-ff-rsync-progress-svg": {
    "fg": "white",
    "bg": "black"
  },
  "helm-ff-rsync-progress-3": {
    "bg": "white"
  },
  "helm-ff-rsync-progress-2": {
    "bg": "orange"
  },
  "helm-ff-rsync-progress-1": {
    "fg": "black",
    "bg": "CadetBlue"
  },
  "helm-ff-rsync-progress": {
    "fg": "#5b4343",
    "bg": "#f6cfcb"
  },
  "helm-delete-async-message": {
    "fg": "yellow"
  },
  "helm-history-remote": {
    "fg": "IndianRed1"
  },
  "helm-history-deleted": {
    "fg": "black",
    "bg": "red"
  },
  "helm-ff-backup-file": {
    "fg": "DimGray"
  },
  "helm-ff-file-extension": {
    "fg": "magenta"
  },
  "helm-ff-pipe": {
    "fg": "yellow",
    "bg": "black"
  },
  "helm-ff-socket": {
    "fg": "DeepPink"
  },
  "helm-ff-dirs": {
    "fg": "#605a52"
  },
  "helm-ff-truename": {
    "fg": "#525643",
    "bg": "#e2e9c1"
  },
  "helm-ff-nofile": {
    "fg": "#605a52"
  },
  "helm-ff-file": {
    "fg": "#605a52"
  },
  "helm-ff-denied": {
    "fg": "red",
    "bg": "black"
  },
  "helm-ff-invalid-symlink": {
    "fg": "black",
    "bg": "red"
  },
  "helm-ff-symlink": {
    "fg": "#b9a992"
  },
  "helm-ff-dotted-symlink-directory": {
    "fg": "DarkOrange",
    "bg": "DimGray"
  },
  "helm-ff-dotted-directory": {
    "fg": "#b9a992"
  },
  "helm-ff-directory": {
    "fg": "#634963"
  },
  "helm-ff-suid": {
    "fg": "white",
    "bg": "red"
  },
  "helm-ff-executable": {
    "fg": "#1b2229"
  },
  "helm-ff-prefix": {
    "fg": "#955f5f"
  },
  "image-dired-thumb-flagged": {
    "bg": "Red3"
  },
  "image-dired-thumb-mark": {
    "bg": "DarkOrange"
  },
  "image-dired-thumb-header-image-count": {
    "bg": "#e4ddd2"
  },
  "image-dired-thumb-header-file-size": {
    "fg": "cadet blue"
  },
  "image-dired-thumb-header-directory-name": {
    "bg": "#e4ddd2"
  },
  "shell-highlight-undef-alias-face": {
    "fg": "#4c5361",
    "bg": "#dde4f2"
  },
  "shell-highlight-undef-undefined-face": {
    "fg": "#5b4343",
    "bg": "#f6cfcb"
  },
  "shell-highlight-undef-defined-face": {
    "fg": "#605a52"
  },
  "helm-buffer-archive": {
    "fg": "gold"
  },
  "helm-buffer-file": {
    "fg": "#605a52"
  },
  "helm-buffer-directory": {
    "fg": "DarkRed",
    "bg": "LightGray"
  },
  "helm-buffer-process": {
    "fg": "sienna3"
  },
  "helm-buffer-size": {
    "fg": "SlateGray"
  },
  "helm-indirect-buffer": {
    "fg": "DimGray",
    "bg": "black"
  },
  "helm-no-file-buffer-modified": {
    "fg": "orange",
    "bg": "black"
  },
  "helm-buffer-modified": {
    "fg": "#b9a992"
  },
  "helm-buffer-not-saved": {
    "fg": "IndianRed2"
  },
  "helm-buffer-saved-out": {
    "fg": "red",
    "bg": "black"
  },
  "all-the-icons-dsilver": {
    "fg": "#c0b19c"
  },
  "all-the-icons-lsilver": {
    "fg": "#eae5de"
  },
  "all-the-icons-silver": {
    "fg": "#d8cfc3"
  },
  "all-the-icons-dpink": {
    "fg": "#a47777"
  },
  "all-the-icons-lpink": {
    "fg": "#cfb7b7"
  },
  "all-the-icons-pink": {
    "fg": "#ba9797"
  },
  "all-the-icons-dcyan": {
    "fg": "#5f8c7d"
  },
  "all-the-icons-lcyan": {
    "fg": "#8faea3"
  },
  "all-the-icons-cyan-alt": {
    "fg": "#5f8c7d"
  },
  "all-the-icons-cyan": {
    "fg": "#5f8c7d"
  },
  "all-the-icons-dorange": {
    "fg": "#685842"
  },
  "all-the-icons-lorange": {
    "fg": "#b4a58f"
  },
  "all-the-icons-orange": {
    "fg": "#957f5f"
  },
  "all-the-icons-dpurple": {
    "fg": "#6d506d"
  },
  "all-the-icons-lpurple": {
    "fg": "#b99db9"
  },
  "all-the-icons-purple-alt": {
    "fg": "#b4a093"
  },
  "all-the-icons-purple": {
    "fg": "#9c739c"
  },
  "all-the-icons-dmaroon": {
    "fg": "#6d506d"
  },
  "all-the-icons-lmaroon": {
    "fg": "#b99db9"
  },
  "all-the-icons-maroon": {
    "fg": "#9c739c"
  },
  "all-the-icons-dblue": {
    "fg": "#7382a0"
  },
  "all-the-icons-lblue": {
    "fg": "#9da7bc"
  },
  "all-the-icons-blue-alt": {
    "fg": "#5f8c7d"
  },
  "all-the-icons-blue": {
    "fg": "#7382a0"
  },
  "all-the-icons-dyellow": {
    "fg": "#685842"
  },
  "all-the-icons-lyellow": {
    "fg": "#b4a58f"
  },
  "all-the-icons-yellow": {
    "fg": "#957f5f"
  },
  "all-the-icons-dgreen": {
    "fg": "#5a5f41"
  },
  "all-the-icons-lgreen": {
    "fg": "#a6ac8d"
  },
  "all-the-icons-green": {
    "fg": "#81895d"
  },
  "all-the-icons-red-alt": {
    "fg": "#b39d8a"
  },
  "all-the-icons-dred": {
    "fg": "#684242"
  },
  "all-the-icons-lred": {
    "fg": "#b48f8f"
  },
  "all-the-icons-red": {
    "fg": "#955f5f"
  },
  "helm-resume-need-update": {
    "bg": "red"
  },
  "helm-moccur-buffer": {
    "fg": "#7382a0"
  },
  "helm-etags-file": {
    "fg": "Lightgoldenrod4"
  },
  "helm-locate-finish": {
    "fg": "Green"
  },
  "helm-grep-cmd-line": {
    "fg": "#605a52",
    "bg": "#f7f3ee"
  },
  "helm-grep-finish": {
    "fg": "#81895d"
  },
  "helm-grep-lineno": {
    "fg": "#605a52"
  },
  "helm-grep-file": {
    "fg": "#5f8c7d"
  },
  "helm-grep-match": {
    "fg": "#7382a0"
  },
  "helm-tooltip": {
    "fg": "black",
    "bg": "goldenrod"
  },
  "helm-match-item": {
    "fg": "#4c5361",
    "bg": "#e8e4ff"
  },
  "helm-selection-line": {
    "fg": "#f1ece4",
    "bg": "#7382a0"
  },
  "helm-helper": {
    "bg": "#e4ddd2"
  },
  "helm-dim-prompt": {
    "fg": "#605a52"
  },
  "helm-mark-prefix": {
    "fg": "#605a52",
    "bg": "#f7f3ee"
  },
  "helm-eob-line": {
    "fg": "#605a52",
    "bg": "#f7f3ee"
  },
  "helm-minibuffer-prompt": {
    "fg": "#7382a0"
  },
  "helm-header-line-left-margin": {
    "fg": "black",
    "bg": "yellow"
  },
  "helm-match": {
    "fg": "#7382a0"
  },
  "helm-prefarg": {
    "fg": "red"
  },
  "helm-separator": {
    "fg": "#ffbfb5"
  },
  "helm-selection": {
    "bg": "#7382a0"
  },
  "helm-candidate-number-suspended": {
    "fg": "black",
    "bg": "#faffb5"
  },
  "helm-candidate-number": {
    "fg": "black",
    "bg": "#faffb5"
  },
  "helm-header": {
    "bg": "#e4ddd2"
  },
  "helm-visible-mark": {
    "fg": "#f1ece4",
    "bg": "#7382a0"
  },
  "helm-source-header": {
    "fg": "#955f5f",
    "bg": "#dcd3c6"
  },
  "company-template-field": {
    "fg": "#81895d",
    "bg": "#f1ece4"
  },
  "company-echo-common": {
    "fg": "firebrick4"
  },
  "company-preview-search": {
    "fg": "#f7f3ee",
    "bg": "#7382a0"
  },
  "company-preview-common": {
    "fg": "#7382a0",
    "bg": "#b9a992"
  },
  "company-preview": {
    "fg": "#b9a992"
  },
  "company-tooltip-scrollbar-track": {
    "fg": "#605a52",
    "bg": "#f1ece4"
  },
  "company-tooltip-scrollbar-thumb": {
    "bg": "#7382a0"
  },
  "company-tooltip-quick-access-selection": {
    "fg": "#614c61"
  },
  "company-tooltip-quick-access": {
    "fg": "#9c739c"
  },
  "company-tooltip-annotation-selection": {
    "fg": "#614c61"
  },
  "company-tooltip-annotation": {
    "fg": "#9c739c"
  },
  "company-tooltip-common-selection": {
    "fg": "#7382a0"
  },
  "company-tooltip-common": {
    "fg": "#7382a0"
  },
  "company-tooltip-mouse": {
    "fg": "#f7f3ee",
    "bg": "#9c739c"
  },
  "company-tooltip-search-selection": {
    "bg": "#dde4f2"
  },
  "company-tooltip-search": {
    "fg": "#f7f3ee",
    "bg": "#7382a0"
  },
  "company-tooltip-selection": {
    "bg": "#e8e4ff"
  },
  "company-tooltip": {
    "fg": "#605a52",
    "bg": "#f1ece4"
  },
  "xref-match": {
    "fg": "#81895d",
    "bg": "#f1ece4"
  },
  "xref-line-number": {
    "fg": "#7382a0"
  },
  "xref-file-header": {
    "fg": "#81895d"
  },
  "eval-sexp-fu-flash-error": {
    "fg": "red"
  },
  "eval-sexp-fu-flash": {
    "bg": "slate blue"
  },
  "vc-git-log-edit-summary-max-warning": {
    "fg": "#955f5f"
  },
  "vc-git-log-edit-summary-target-warning": {
    "fg": "#957f5f"
  },
  "copilot-overlay-face": {
    "fg": "#605a52"
  },
  "flycheck-error-list-checker-name": {
    "fg": "#605a52"
  },
  "flycheck-error-list-id-with-explainer": {
    "fg": "#605a52",
    "bg": "#f7f3ee"
  },
  "flycheck-error-list-id": {
    "fg": "#605a52",
    "bg": "#f7f3ee"
  },
  "flycheck-error-list-info": {
    "fg": "#81895d"
  },
  "flycheck-error-list-warning": {
    "fg": "#957f5f"
  },
  "flycheck-error-list-error": {
    "fg": "#955f5f"
  },
  "flycheck-fringe-info": {
    "fg": "#81895d",
    "bg": "#f7f3ee"
  },
  "flycheck-fringe-warning": {
    "fg": "#957f5f",
    "bg": "#f7f3ee"
  },
  "flycheck-fringe-error": {
    "fg": "#955f5f",
    "bg": "#f7f3ee"
  },
  "highlight-numbers-number": {
    "fg": "#465953",
    "bg": "#d2ebe3"
  },
  "rainbow-delimiters-depth-1-face": {
    "fg": "#7382a0"
  },
  "rainbow-delimiters-depth-2-face": {
    "fg": "#9c739c"
  },
  "rainbow-delimiters-depth-3-face": {
    "fg": "#81895d"
  },
  "rainbow-delimiters-depth-4-face": {
    "fg": "#957f5f"
  },
  "rainbow-delimiters-depth-5-face": {
    "fg": "#5f8c7d"
  },
  "rainbow-delimiters-depth-6-face": {
    "fg": "#955f5f"
  },
  "rainbow-delimiters-depth-7-face": {
    "fg": "#81895d"
  },
  "rainbow-delimiters-depth-8-face": {
    "fg": "#81895d"
  },
  "rainbow-delimiters-depth-9-face": {
    "fg": "#9c739c"
  },
  "rainbow-delimiters-mismatched-face": {
    "fg": "#955f5f"
  },
  "rainbow-delimiters-unmatched-face": {
    "fg": "#955f5f"
  },
  "rainbow-delimiters-base-error-face": {
    "fg": "#955f5f",
    "bg": "#f7f3ee"
  },
  "rainbow-delimiters-base-face": {
    "fg": "#605a52",
    "bg": "#f7f3ee"
  },
  "sp-show-pair-enclosing": {
    "fg": "#f1ece4",
    "bg": "#7382a0"
  },
  "sp-show-pair-mismatch-face": {
    "fg": "#f1ece4",
    "bg": "#955f5f"
  },
  "sp-show-pair-match-face": {
    "fg": "#955f5f",
    "bg": "#f1ece4"
  },
  "sp-wrap-tag-overlay-face": {
    "fg": "#4c5361",
    "bg": "#e8e4ff"
  },
  "sp-wrap-overlay-closing-pair": {
    "fg": "red",
    "bg": "#e8e4ff"
  },
  "sp-wrap-overlay-opening-pair": {
    "fg": "green",
    "bg": "#e8e4ff"
  },
  "sp-wrap-overlay-face": {
    "fg": "#4c5361",
    "bg": "#e8e4ff"
  },
  "sp-pair-overlay-face": {
    "fg": "#4c5361",
    "bg": "#e8e4ff"
  },
  "yas-field-highlight-face": {
    "fg": "#81895d",
    "bg": "#f1ece4"
  },
  "spaceline-python-venv": {
    "fg": "#9c739c"
  },
  "spaceline-flycheck-info": {
    "fg": "#81895d"
  },
  "spaceline-flycheck-warning": {
    "fg": "#957f5f"
  },
  "spaceline-flycheck-error": {
    "fg": "#955f5f"
  },
  "spaceline-read-only": {
    "fg": "#3E3D31",
    "bg": "plum3"
  },
  "spaceline-modified": {
    "bg": "#957f5f"
  },
  "spaceline-unmodified": {
    "bg": "#9c739c"
  },
  "spaceline-evil-motion": {
    "bg": "#9c739c"
  },
  "spaceline-evil-visual": {
    "bg": "#b9a992"
  },
  "spaceline-evil-replace": {
    "bg": "#957f5f"
  },
  "spaceline-evil-emacs": {
    "bg": "#5f8c7d"
  },
  "spaceline-evil-insert": {
    "bg": "#81895d"
  },
  "spaceline-evil-normal": {
    "bg": "#7382a0"
  },
  "spaceline-highlight-face": {
    "bg": "#7382a0"
  },
  "powerline-inactive2": {
    "fg": "#93836c",
    "bg": "#ddd4c8"
  },
  "powerline-inactive1": {
    "fg": "#93836c",
    "bg": "#dcd3c7"
  },
  "powerline-inactive0": {
    "fg": "#93836c",
    "bg": "#dcd3c6"
  },
  "powerline-active2": {
    "fg": "#1b2229",
    "bg": "#f7f3ef"
  },
  "powerline-active1": {
    "bg": "#f7f3ee"
  },
  "powerline-active0": {
    "bg": "#f7f3ee"
  },
  "diff-hl-change": {
    "fg": "#957f5f",
    "bg": "#957f5f"
  },
  "diff-hl-delete": {
    "fg": "#955f5f",
    "bg": "#955f5f"
  },
  "diff-hl-insert": {
    "fg": "#81895d",
    "bg": "#81895d"
  },
  "log-view-commit-body": {
    "fg": "#b9a992"
  },
  "log-view-message": {
    "bg": "grey85"
  },
  "log-view-file": {
    "bg": "grey70"
  },
  "log-edit-unknown-header": {
    "fg": "#b9a992"
  },
  "log-edit-header": {
    "fg": "#614c61",
    "bg": "#f1ddf1"
  },
  "log-edit-summary": {
    "fg": "#605a52"
  },
  "message-mml": {
    "fg": "#b9a992"
  },
  "message-cited-text-4": {
    "fg": "#81895d"
  },
  "message-cited-text-3": {
    "fg": "#81895d"
  },
  "message-cited-text-2": {
    "fg": "#9c739c"
  },
  "message-cited-text-1": {
    "fg": "#9c739c"
  },
  "message-separator": {
    "fg": "#b9a992"
  },
  "message-header-xheader": {
    "fg": "#9d8f7c"
  },
  "message-header-name": {
    "fg": "#81895d"
  },
  "message-header-other": {
    "fg": "#9c739c"
  },
  "message-header-newsgroups": {
    "fg": "#957f5f"
  },
  "message-header-subject": {
    "fg": "#7382a0"
  },
  "message-header-cc": {
    "fg": "#616e88"
  },
  "message-header-to": {
    "fg": "#7382a0"
  },
  "epa-mark": {
    "fg": "red"
  },
  "epa-string": {
    "fg": "blue4"
  },
  "mm-command-output": {
    "fg": "red3"
  },
  "change-log-acknowledgment": {
    "fg": "#b9a992"
  },
  "change-log-function": {
    "fg": "#4c5361",
    "bg": "#dde4f2"
  },
  "change-log-conditionals": {
    "fg": "#4c5361",
    "bg": "#dde4f2"
  },
  "change-log-list": {
    "fg": "#614c61",
    "bg": "#f1ddf1"
  },
  "change-log-file": {
    "fg": "#605a52"
  },
  "change-log-email": {
    "fg": "#4c5361",
    "bg": "#dde4f2"
  },
  "change-log-name": {
    "fg": "#465953",
    "bg": "#d2ebe3"
  },
  "change-log-date": {
    "fg": "#525643",
    "bg": "#e2e9c1"
  },
  "vc-dir-status-ignored": {
    "fg": "#605a52"
  },
  "vc-dir-status-up-to-date": {
    "fg": "#605a52"
  },
  "vc-dir-status-edited": {
    "fg": "#4c5361",
    "bg": "#dde4f2"
  },
  "vc-dir-status-warning": {
    "fg": "#5b4343",
    "bg": "#f6cfcb"
  },
  "vc-dir-mark-indicator": {
    "fg": "#605a52",
    "bg": "#f7f3ee"
  },
  "vc-dir-file": {
    "fg": "#605a52"
  },
  "vc-dir-directory": {
    "fg": "#b9a992"
  },
  "vc-dir-header-value": {
    "fg": "#4c5361",
    "bg": "#dde4f2"
  },
  "vc-dir-header": {
    "fg": "#605a52",
    "bg": "#f7f3ee"
  },
  "diff-refine-added": {
    "fg": "#81895d",
    "bg": "#f1ece4"
  },
  "diff-refine-removed": {
    "fg": "#955f5f",
    "bg": "#f6cfcb"
  },
  "diff-refine-changed": {
    "fg": "#9c739c"
  },
  "diff-error": {
    "fg": "red",
    "bg": "black"
  },
  "diff-nonexistent": {
    "fg": "#7382a0"
  },
  "diff-context": {
    "fg": "#736d66"
  },
  "diff-function": {
    "fg": "#5f8c7d"
  },
  "diff-indicator-changed": {
    "fg": "#957f5f"
  },
  "diff-indicator-added": {
    "fg": "#81895d"
  },
  "diff-indicator-removed": {
    "fg": "#81895d"
  },
  "diff-changed": {
    "fg": "#9c739c"
  },
  "diff-changed-unspecified": {
    "fg": "#9c739c",
    "bg": "grey90"
  },
  "diff-added": {
    "fg": "#81895d",
    "bg": "#f1ece4"
  },
  "diff-removed": {
    "fg": "#955f5f",
    "bg": "#f6cfcb"
  },
  "diff-hunk-header": {
    "fg": "#9c739c"
  },
  "diff-index": {
    "fg": "#7382a0"
  },
  "diff-file-header": {
    "fg": "#7382a0"
  },
  "diff-header": {
    "fg": "#5f8c7d"
  },
  "grep-heading": {
    "fg": "#81895d"
  },
  "winum-face": {
    "fg": "#7382a0"
  },
  "imenu-list-entry-subalist-face-3": {
    "fg": "orange red"
  },
  "imenu-list-entry-face-3": {
    "fg": "orange red"
  },
  "imenu-list-entry-subalist-face-2": {
    "fg": "#957f5f"
  },
  "imenu-list-entry-face-2": {
    "fg": "#957f5f"
  },
  "imenu-list-entry-subalist-face-1": {
    "fg": "#81895d"
  },
  "imenu-list-entry-face-1": {
    "fg": "#81895d"
  },
  "imenu-list-entry-subalist-face-0": {
    "fg": "#7382a0"
  },
  "imenu-list-entry-face-0": {
    "fg": "#7382a0"
  },
  "hs-ellipsis": {
    "fg": "#605a52",
    "bg": "#f7f3ee"
  },
  "ibuffer-locked-buffer": {
    "fg": "brown4"
  },
  "dired-ignored": {
    "fg": "#b9a992"
  },
  "dired-special": {
    "fg": "#4c5361",
    "bg": "#dde4f2"
  },
  "dired-broken-symlink": {
    "fg": "yellow1",
    "bg": "red1"
  },
  "dired-symlink": {
    "fg": "#5f8c7d"
  },
  "dired-directory": {
    "fg": "#9c739c"
  },
  "dired-set-id": {
    "fg": "#5b4343",
    "bg": "#f6cfcb"
  },
  "dired-perm-write": {
    "fg": "#605a52"
  },
  "dired-warning": {
    "fg": "#957f5f"
  },
  "dired-flagged": {
    "fg": "#955f5f"
  },
  "dired-marked": {
    "fg": "#9c739c"
  },
  "dired-mark": {
    "fg": "#957f5f"
  },
  "dired-header": {
    "fg": "#7382a0"
  },
  "vhl/default-face": {
    "bg": "#b9a992"
  },
  "symbol-overlay-face-8": {
    "bg": "#d8ded7"
  },
  "symbol-overlay-face-7": {
    "bg": "#c7c8b3"
  },
  "symbol-overlay-face-6": {
    "bg": "#dbccd5"
  },
  "symbol-overlay-face-5": {
    "bg": "#d9c6c3"
  },
  "symbol-overlay-face-4": {
    "bg": "#d9d0c3"
  },
  "symbol-overlay-face-3": {
    "bg": "#d9d0c3"
  },
  "symbol-overlay-face-2": {
    "bg": "#d2bfcd"
  },
  "symbol-overlay-face-1": {
    "bg": "#c2c5ce"
  },
  "symbol-overlay-default-face": {
    "bg": "#c2beb8"
  },
  "persp-face-lighter-default": {
    "fg": "#7382a0"
  },
  "persp-face-lighter-nil-persp": {
    "fg": "#b9a992"
  },
  "persp-face-lighter-buffer-not-in-persp": {
    "fg": "#9d8f7c"
  },
  "page-break-lines": {
    "fg": "#b9a992"
  },
  "c-annotation-face": {
    "fg": "#465953",
    "bg": "#d2ebe3"
  },
  "hl-todo-flymake-type": {
    "fg": "#614c61",
    "bg": "#f1ddf1"
  },
  "hl-todo": {
    "fg": "#955f5f"
  },
  "eyebrowse-mode-line-active": {
    "fg": "#7382a0"
  },
  "anzu-replace-to": {
    "fg": "#81895d",
    "bg": "#f1ece4"
  },
  "anzu-match-3": {
    "fg": "black",
    "bg": "yellow"
  },
  "anzu-match-2": {
    "fg": "black",
    "bg": "springgreen"
  },
  "anzu-match-1": {
    "fg": "black",
    "bg": "aquamarine"
  },
  "anzu-replace-highlight": {
    "fg": "#955f5f",
    "bg": "#f1ece4"
  },
  "anzu-mode-line-no-match": {
    "fg": "magenta"
  },
  "anzu-mode-line": {
    "fg": "magenta"
  },
  "info-variable-ref-item": {
    "fg": "FireBrick",
    "bg": "gray88"
  },
  "info-user-option-ref-item": {
    "fg": "Red",
    "bg": "gray88"
  },
  "info-syntax-class-item": {
    "fg": "DarkGreen",
    "bg": "gray88"
  },
  "info-special-form-ref-item": {
    "fg": "Magenta",
    "bg": "gray88"
  },
  "info-reference-item": {
    "bg": "gray88"
  },
  "info-macro-ref-item": {
    "fg": "DarkMagenta",
    "bg": "gray88"
  },
  "info-function-ref-item": {
    "fg": "DarkBlue",
    "bg": "gray88"
  },
  "info-constant-ref-item": {
    "fg": "DeepPink",
    "bg": "gray88"
  },
  "info-command-ref-item": {
    "fg": "Blue",
    "bg": "gray88"
  },
  "info-isolated-backquote": {
    "fg": "Magenta",
    "bg": "PaleGreen1"
  },
  "info-isolated-quote": {
    "fg": "Magenta",
    "bg": "SlateGray2"
  },
  "info-string": {
    "fg": "red3"
  },
  "info-quoted-name": {
    "fg": "DarkViolet"
  },
  "info-menu": {
    "fg": "Blue"
  },
  "info-homoglyph": {
    "fg": "brown"
  },
  "info-file": {
    "fg": "Blue",
    "bg": "gray88"
  },
  "info-indented-text": {
    "fg": "DarkBlue"
  },
  "info-double-quoted-name": {
    "fg": "DarkOrange"
  },
  "info-custom-delimited": {
    "fg": "Red"
  },
  "which-key-docstring-face": {
    "fg": "#b9a992",
    "bg": "#f1ece4"
  },
  "which-key-special-key-face": {
    "fg": "#81895d"
  },
  "which-key-group-description-face": {
    "fg": "#9c739c"
  },
  "which-key-highlighted-command-face": {
    "fg": "#605a52",
    "bg": "#7382a0"
  },
  "which-key-local-map-description-face": {
    "fg": "#957f5f"
  },
  "which-key-command-description-face": {
    "fg": "#605a52"
  },
  "which-key-note-face": {
    "fg": "#b9a992",
    "bg": "#f1ece4"
  },
  "which-key-separator-face": {
    "fg": "#b9a992",
    "bg": "#f1ece4"
  },
  "which-key-key-face": {
    "fg": "#81895d"
  },
  "hydra-face-teal": {
    "fg": "#5f8c7d"
  },
  "hydra-face-pink": {
    "fg": "#9c739c"
  },
  "hydra-face-amaranth": {
    "fg": "#9c739c"
  },
  "hydra-face-blue": {
    "fg": "#7382a0"
  },
  "hydra-face-red": {
    "fg": "#955f5f"
  },
  "lv-separator": {
    "bg": "grey80"
  },
  "spacemacs-iedit-insert-face": {
    "bg": "firebrick1"
  },
  "spacemacs-iedit-face": {
    "bg": "firebrick1"
  },
  "spacemacs-lisp-face": {
    "bg": "HotPink1"
  },
  "spacemacs-motion-face": {
    "bg": "plum3"
  },
  "spacemacs-visual-face": {
    "bg": "SteelBlue3"
  },
  "spacemacs-evilified-face": {
    "bg": "LightGoldenrod3"
  },
  "spacemacs-replace-face": {
    "bg": "chocolate"
  },
  "spacemacs-hybrid-face": {
    "bg": "SkyBlue2"
  },
  "spacemacs-emacs-face": {
    "bg": "SkyBlue2"
  },
  "spacemacs-insert-face": {
    "bg": "chartreuse3"
  },
  "spacemacs-normal-face": {
    "bg": "DarkGoldenrod2"
  },
  "rectangle-preview": {
    "bg": "#d8d4cd"
  },
  "evil-ex-substitute-replacement": {
    "fg": "#81895d",
    "bg": "#f1ece4"
  },
  "evil-ex-substitute-matches": {
    "fg": "#955f5f",
    "bg": "#f1ece4"
  },
  "evil-ex-lazy-highlight": {
    "fg": "#4c5361",
    "bg": "#e8e4ff"
  },
  "evil-ex-search": {
    "fg": "#f1ece4",
    "bg": "#7382a0"
  },
  "evil-ex-info": {
    "fg": "#955f5f"
  },
  "edmacro-label": {
    "fg": "DarkBlue"
  },
  "kmacro-menu-marked": {
    "fg": "#957f5f"
  },
  "kmacro-menu-flagged": {
    "fg": "#955f5f"
  },
  "kmacro-menu-mark": {
    "fg": "#465953",
    "bg": "#d2ebe3"
  },
  "info-index-match": {
    "fg": "#81895d",
    "bg": "#f1ece4"
  },
  "info-header-node": {
    "fg": "brown"
  },
  "info-header-xref": {
    "fg": "#7382a0"
  },
  "info-xref-visited": {
    "fg": "magenta4"
  },
  "info-xref": {
    "fg": "#7382a0"
  },
  "info-menu-star": {
    "fg": "red1"
  },
  "info-node": {
    "fg": "brown"
  },
  "hl-line": {
    "bg": "#f1ece4"
  },
  "spacemacs-helm-navigation-ts-face": {
    "fg": "black",
    "bg": "red"
  },
  "compilation-column-number": {
    "fg": "#b9a992"
  },
  "compilation-line-number": {
    "fg": "#7382a0"
  },
  "compilation-mode-line-exit": {
    "fg": "#81895d"
  },
  "compilation-mode-line-run": {
    "fg": "#957f5f"
  },
  "compilation-mode-line-fail": {
    "fg": "#955f5f"
  },
  "compilation-info": {
    "fg": "#81895d"
  },
  "compilation-warning": {
    "fg": "#957f5f"
  },
  "compilation-error": {
    "fg": "#955f5f"
  },
  "comint-highlight-prompt": {
    "fg": "#7382a0"
  },
  "ansi-color-bright-white": {
    "fg": "#1b2229",
    "bg": "#1b2229"
  },
  "ansi-color-bright-cyan": {
    "fg": "#779d90",
    "bg": "#779d90"
  },
  "ansi-color-bright-magenta": {
    "fg": "#aa88aa",
    "bg": "#aa88aa"
  },
  "ansi-color-bright-blue": {
    "fg": "#8894ae",
    "bg": "#8894ae"
  },
  "ansi-color-bright-yellow": {
    "fg": "#a49277",
    "bg": "#a49277"
  },
  "ansi-color-bright-green": {
    "fg": "#939a75",
    "bg": "#939a75"
  },
  "ansi-color-bright-red": {
    "fg": "#a47777",
    "bg": "#a47777"
  },
  "ansi-color-bright-black": {
    "fg": "#93836c",
    "bg": "#93836c"
  },
  "ansi-color-white": {
    "fg": "#605a52",
    "bg": "#605a52"
  },
  "ansi-color-cyan": {
    "fg": "#5f8c7d",
    "bg": "#5f8c7d"
  },
  "ansi-color-magenta": {
    "fg": "#9c739c",
    "bg": "#9c739c"
  },
  "ansi-color-blue": {
    "fg": "#7382a0",
    "bg": "#7382a0"
  },
  "ansi-color-yellow": {
    "fg": "#957f5f",
    "bg": "#957f5f"
  },
  "ansi-color-green": {
    "fg": "#81895d",
    "bg": "#81895d"
  },
  "ansi-color-red": {
    "fg": "#955f5f",
    "bg": "#955f5f"
  },
  "ansi-color-black": {
    "fg": "#f7f3ee",
    "bg": "#f7f3ee"
  },
  "spacemacs-transient-state-title-face": {
    "bg": "#e4ddd2"
  },
  "spacemacs-micro-state-binding-face": {
    "fg": "#955f5f"
  },
  "spacemacs-micro-state-header-face": {
    "fg": "black",
    "bg": "DarkGoldenrod2"
  },
  "org-kbd": {
    "fg": "black",
    "bg": "LemonChiffon1"
  },
  "spacemacs-mode-line-new-version-lighter-success-face": {
    "fg": "#81895d"
  },
  "spacemacs-mode-line-new-version-lighter-warning-face": {
    "fg": "#957f5f"
  },
  "spacemacs-mode-line-new-version-lighter-error-face": {
    "fg": "#955f5f"
  },
  "package-status-avail-obso": {
    "fg": "#955f5f"
  },
  "package-status-incompat": {
    "fg": "#955f5f"
  },
  "package-status-unsigned": {
    "fg": "#5b4343",
    "bg": "#f6cfcb"
  },
  "package-status-dependency": {
    "fg": "#b9a992"
  },
  "package-status-from-source": {
    "fg": "#605a52",
    "bg": "#f7f3ee"
  },
  "package-status-installed": {
    "fg": "#b9a992"
  },
  "package-status-disabled": {
    "fg": "#5b4343",
    "bg": "#f6cfcb"
  },
  "package-status-held": {
    "fg": "#465953",
    "bg": "#d2ebe3"
  },
  "package-status-new": {
    "fg": "#605a52",
    "bg": "#f7f3ee"
  },
  "package-status-available": {
    "fg": "#605a52",
    "bg": "#f7f3ee"
  },
  "package-status-external": {
    "fg": "#605a52"
  },
  "package-status-built-in": {
    "fg": "#605a52"
  },
  "package-description": {
    "fg": "#605a52",
    "bg": "#f7f3ee"
  },
  "package-name": {
    "fg": "#7382a0"
  },
  "package-help-section-name": {
    "fg": "#605a52"
  },
  "browse-url-button": {
    "fg": "#7382a0"
  },
  "custom-group-subtitle": {
    "fg": "#955f5f"
  },
  "custom-group-tag": {
    "fg": "#9c739c"
  },
  "custom-group-tag-1": {
    "fg": "#7382a0"
  },
  "custom-face-tag": {
    "fg": "#9c739c"
  },
  "custom-visibility": {
    "fg": "#7382a0"
  },
  "custom-variable-button": {
    "fg": "#81895d"
  },
  "custom-variable-tag": {
    "fg": "#9c739c"
  },
  "custom-variable-obsolete": {
    "fg": "#b9a992",
    "bg": "#f7f3ee"
  },
  "custom-comment-tag": {
    "fg": "#b9a992"
  },
  "custom-comment": {
    "fg": "#605a52",
    "bg": "#d8d4cd"
  },
  "custom-link": {
    "fg": "#7382a0"
  },
  "custom-state": {
    "fg": "#81895d",
    "bg": "#dfddd1"
  },
  "custom-button-pressed-unraised": {
    "fg": "#f7f3ee",
    "bg": "#9c739c"
  },
  "custom-button-pressed": {
    "fg": "#f7f3ee",
    "bg": "#7382a0"
  },
  "custom-button-unraised": {
    "fg": "#9c739c",
    "bg": "#f7f3ee"
  },
  "custom-button-mouse": {
    "fg": "#f7f3ee",
    "bg": "#7382a0"
  },
  "custom-button": {
    "fg": "#7382a0",
    "bg": "#f7f3ee"
  },
  "custom-saved": {
    "fg": "#81895d",
    "bg": "#dfddd1"
  },
  "custom-themed": {
    "fg": "#957f5f",
    "bg": "#f7f3ee"
  },
  "custom-changed": {
    "fg": "#7382a0",
    "bg": "#f7f3ee"
  },
  "custom-set": {
    "fg": "#957f5f",
    "bg": "#f7f3ee"
  },
  "custom-modified": {
    "fg": "#7382a0",
    "bg": "#dcdcde"
  },
  "custom-rogue": {
    "fg": "pink",
    "bg": "black"
  },
  "custom-invalid": {
    "fg": "#955f5f",
    "bg": "#e3d5d1"
  },
  "icon-button": {
    "fg": "black",
    "bg": "#808080"
  },
  "widget-button-pressed": {
    "fg": "#955f5f"
  },
  "widget-unselected": {
    "fg": "#605a52"
  },
  "widget-inactive": {
    "fg": "#605a52"
  },
  "widget-single-line-field": {
    "bg": "#b9a992"
  },
  "widget-field": {
    "bg": "#b9a992"
  },
  "widget-documentation": {
    "fg": "#81895d"
  },
  "tooltip": {
    "fg": "#605a52",
    "bg": "#f1ece4"
  },
  "elisp-shorthand-font-lock-face": {
    "fg": "cyan",
    "bg": "#f1ddf1"
  },
  "match": {
    "fg": "#81895d",
    "bg": "#f1ece4"
  },
  "query-replace": {
    "fg": "#4c5361",
    "bg": "#e8e4ff"
  },
  "tab-bar-tab-highlight": {
    "fg": "black",
    "bg": "grey85"
  },
  "tab-bar-tab-ungrouped": {
    "fg": "#605a52",
    "bg": "#f1ece4"
  },
  "tab-bar-tab-group-inactive": {
    "fg": "#605a52",
    "bg": "#f1ece4"
  },
  "tab-bar-tab-group-current": {
    "fg": "#605a52",
    "bg": "#f7f3ee"
  },
  "tab-bar-tab-inactive": {
    "fg": "#93836c",
    "bg": "#f1ece4"
  },
  "tab-bar-tab": {
    "fg": "#605a52",
    "bg": "#f7f3ee"
  },
  "file-name-shadow": {
    "fg": "#605a52"
  },
  "isearch-group-2": {
    "fg": "lightskyblue1",
    "bg": "#a000a0"
  },
  "isearch-group-1": {
    "fg": "lightskyblue1",
    "bg": "#f000f0"
  },
  "lazy-highlight": {
    "fg": "#4c5361",
    "bg": "#e8e4ff"
  },
  "isearch-fail": {
    "fg": "#f1ece4",
    "bg": "#955f5f"
  },
  "isearch": {
    "fg": "#4c5361",
    "bg": "#e8e4ff"
  },
  "mouse-drag-and-drop-region": {
    "bg": "#d8d4cd"
  },
  "font-lock-property-use-face": {
    "fg": "#4c5361",
    "bg": "#dde4f2"
  },
  "font-lock-property-name-face": {
    "fg": "#4c5361",
    "bg": "#dde4f2"
  },
  "font-lock-number-face": {
    "fg": "#957f5f"
  },
  "font-lock-escape-face": {
    "fg": "#605a52",
    "bg": "#f7f3ee"
  },
  "font-lock-regexp-grouping-construct": {
    "fg": "#605a52",
    "bg": "#f7f3ee"
  },
  "font-lock-regexp-grouping-backslash": {
    "fg": "#605a52",
    "bg": "#f7f3ee"
  },
  "font-lock-regexp-face": {
    "fg": "#525643",
    "bg": "#e2e9c1"
  },
  "font-lock-preprocessor-face": {
    "fg": "#605a52",
    "bg": "#f7f3ee"
  },
  "font-lock-negation-char-face": {
    "fg": "#605a52",
    "bg": "#f7f3ee"
  },
  "font-lock-warning-face": {
    "fg": "#5b4343",
    "bg": "#f6cfcb"
  },
  "font-lock-constant-face": {
    "fg": "#465953",
    "bg": "#d2ebe3"
  },
  "font-lock-type-face": {
    "fg": "#605a52",
    "bg": "#f7f3ee"
  },
  "font-lock-variable-use-face": {
    "fg": "#4c5361",
    "bg": "#dde4f2"
  },
  "font-lock-variable-name-face": {
    "fg": "#4c5361",
    "bg": "#dde4f2"
  },
  "font-lock-function-call-face": {
    "fg": "#605a52"
  },
  "font-lock-function-name-face": {
    "fg": "#605a52"
  },
  "font-lock-builtin-face": {
    "fg": "#605a52"
  },
  "font-lock-keyword-face": {
    "fg": "#614c61",
    "bg": "#f1ddf1"
  },
  "font-lock-doc-markup-face": {
    "fg": "#465953",
    "bg": "#d2ebe3"
  },
  "font-lock-doc-face": {
    "fg": "#9d8f7c"
  },
  "font-lock-string-face": {
    "fg": "#525643",
    "bg": "#e2e9c1"
  },
  "font-lock-comment-delimiter-face": {
    "fg": "#b9a992"
  },
  "font-lock-comment-face": {
    "fg": "#b9a992"
  },
  "completions-common-part": {
    "fg": "blue3"
  },
  "completions-highlight": {
    "fg": "#f1ece4",
    "bg": "#7382a0"
  },
  "completions-annotations": {
    "fg": "#605a52"
  },
  "completions-group-separator": {
    "fg": "#605a52"
  },
  "completions-group-title": {
    "fg": "#605a52"
  },
  "blink-matching-paren-offscreen": {
    "fg": "green"
  },
  "separator-line": {
    "bg": "#a0a0a0"
  },
  "next-error-message": {
    "fg": "#f1ece4",
    "bg": "#7382a0"
  },
  "next-error": {
    "bg": "#d8d4cd"
  },
  "abbrev-table-name": {
    "fg": "#605a52"
  },
  "button": {
    "fg": "#7382a0"
  },
  "show-paren-mismatch": {
    "fg": "#f1ece4",
    "bg": "#955f5f"
  },
  "show-paren-match-expression": {
    "fg": "#955f5f",
    "bg": "#f1ece4"
  },
  "show-paren-match": {
    "fg": "#955f5f",
    "bg": "#f1ece4"
  },
  "tty-menu-selected-face": {
    "bg": "red"
  },
  "tty-menu-disabled-face": {
    "fg": "lightgray",
    "bg": "blue"
  },
  "tty-menu-enabled-face": {
    "fg": "yellow",
    "bg": "blue"
  },
  "read-multiple-choice-face": {
    "fg": "DarkBlue",
    "bg": "grey96"
  },
  "success": {
    "fg": "#81895d"
  },
  "warning": {
    "fg": "#957f5f"
  },
  "error": {
    "fg": "#955f5f"
  },
  "help-key-binding": {
    "fg": "DarkBlue",
    "bg": "grey96"
  },
  "tab-line": {
    "fg": "#f1ece4",
    "bg": "#f1ece4"
  },
  "tab-bar": {
    "fg": "#f1ece4",
    "bg": "#f1ece4"
  },
  "tool-bar": {
    "fg": "black",
    "bg": "grey75"
  },
  "cursor": {
    "bg": "#7382a0"
  },
  "fringe": {
    "fg": "#93836c",
    "bg": "#f7f3ee"
  },
  "minibuffer-prompt": {
    "fg": "#7382a0"
  },
  "window-divider-last-pixel": {
    "fg": "#c6bdb2",
    "bg": "#c6bdb2"
  },
  "window-divider-first-pixel": {
    "fg": "#c6bdb2",
    "bg": "#c6bdb2"
  },
  "window-divider": {
    "fg": "#c6bdb2",
    "bg": "#c6bdb2"
  },
  "vertical-border": {
    "fg": "#c6bdb2",
    "bg": "#c6bdb2"
  },
  "header-line-inactive": {
    "bg": "#e4ddd2"
  },
  "header-line-active": {
    "bg": "#e4ddd2"
  },
  "header-line-highlight": {
    "fg": "#f1ece4",
    "bg": "#7382a0"
  },
  "header-line": {
    "bg": "#e4ddd2"
  },
  "mode-line-emphasis": {
    "fg": "#7382a0"
  },
  "mode-line-highlight": {
    "fg": "#f1ece4",
    "bg": "#7382a0"
  },
  "mode-line-inactive": {
    "fg": "#93836c",
    "bg": "#dedad6"
  },
  "mode-line-active": {
    "bg": "#e4ddd2"
  },
  "mode-line": {
    "bg": "#e4ddd2"
  },
  "nobreak-hyphen": {
    "fg": "brown"
  },
  "nobreak-space": {
    "fg": "#5f8c7d"
  },
  "homoglyph": {
    "fg": "brown"
  },
  "escape-glyph": {
    "fg": "#5f8c7d"
  },
  "fill-column-indicator": {
    "fg": "#605a52"
  },
  "line-number-minor-tick": {
    "bg": "grey95"
  },
  "line-number-major-tick": {
    "bg": "grey85"
  },
  "line-number-current-line": {
    "fg": "#1b2229",
    "bg": "#f1ece4"
  },
  "line-number": {
    "fg": "#a39582",
    "bg": "#f7f3ee"
  },
  "trailing-whitespace": {
    "bg": "#955f5f"
  },
  "secondary-selection": {
    "bg": "#b9a992"
  },
  "region": {
    "bg": "#d8d4cd"
  },
  "highlight": {
    "fg": "#f1ece4",
    "bg": "#7382a0"
  },
  "link-visited": {
    "fg": "magenta4"
  },
  "link": {
    "fg": "#7382a0"
  },
  "shadow": {
    "fg": "#605a52"
  },
  "default": {
    "fg": "#605a52",
    "bg": "#f7f3ee"
  }
}