{
  "diff-hl-margin-unknown": {
    "fg": "#767676"
  },
  "diff-hl-margin-ignored": {
    "fg": "#767676"
  },
  "diff-hl-margin-change": {
    "fg": "#D8B941",
    "bg": "#D8B941"
  },
  "diff-hl-margin-delete": {
    "fg": "#D83441",
    "bg": "#D83441"
  },
  "diff-hl-margin-insert": {
    "fg": "#79D836",
    "bg": "#79D836"
  },
  "diff-hl-dired-ignored": {
    "fg": "#767676"
  },
  "diff-hl-dired-unknown": {
    "fg": "#767676"
  },
  "diff-hl-dired-change": {
    "fg": "#D8B941",
    "bg": "#D8B941"
  },
  "diff-hl-dired-delete": {
    "fg": "#D83441",
    "bg": "#D83441"
  },
  "diff-hl-dired-insert": {
    "fg": "#79D836",
    "bg": "#79D836"
  },
  "org-indent": {
    "fg": "#0D0E16"
  },
  "org-superstar-first": {
    "fg": "#D85F00"
  },
  "org-superstar-ordered-item": {
    "fg": "#CEDBE5",
    "bg": "#0D0E16"
  },
  "org-superstar-item": {
    "fg": "#CEDBE5",
    "bg": "#0D0E16"
  },
  "org-superstar-leading": {
    "fg": "gray",
    "bg": "#0D0E16"
  },
  "eww-valid-certificate": {
    "fg": "#D85F00"
  },
  "eww-invalid-certificate": {
    "fg": "#D83441"
  },
  "eww-form-textarea": {
    "fg": "#CEDBE5",
    "bg": "#0D0E16"
  },
  "eww-form-text": {
    "fg": "#CEDBE5",
    "bg": "#0D0E16"
  },
  "eww-form-select": {
    "fg": "#CEDBE5",
    "bg": "#040408"
  },
  "eww-form-checkbox": {
    "fg": "#CEDBE5",
    "bg": "#040408"
  },
  "eww-form-file": {
    "fg": "#CEDBE5",
    "bg": "#040408"
  },
  "eww-form-submit": {
    "fg": "#CEDBE5",
    "bg": "#1E1E33"
  },
  "gnus-header-content": {
    "fg": "#AB11D8"
  },
  "gnus-header-name": {
    "fg": "#79D836"
  },
  "gnus-header-newsgroups": {
    "fg": "#AB11D8"
  },
  "gnus-header-subject": {
    "fg": "#D85F00"
  },
  "gnus-header-from": {
    "fg": "#AB11D8"
  },
  "gnus-signature": {
    "fg": "#D8B941"
  },
  "gnus-emphasis-highlight-words": {
    "fg": "yellow",
    "bg": "black"
  },
  "mm-uu-extract": {
    "fg": "#cfc8c2",
    "bg": "#2b222f"
  },
  "shr-mark": {
    "fg": "black",
    "bg": "yellow"
  },
  "shr-h6": {
    "fg": "#CEDBE5",
    "bg": "#0D0E16"
  },
  "shr-h5": {
    "fg": "#CEDBE5",
    "bg": "#0D0E16"
  },
  "shr-h4": {
    "fg": "#CEDBE5",
    "bg": "#0D0E16"
  },
  "shr-selected-link": {
    "fg": "#D85F00",
    "bg": "red"
  },
  "shr-link": {
    "fg": "#D85F00"
  },
  "gnus-splash": {
    "fg": "#cccccc"
  },
  "gnus-summary-low-read": {
    "fg": "#a4afb7"
  },
  "gnus-summary-high-read": {
    "fg": "#d7e2ea"
  },
  "gnus-summary-normal-read": {
    "fg": "#CEDBE5"
  },
  "gnus-summary-low-unread": {
    "fg": "#60ac2b"
  },
  "gnus-summary-high-unread": {
    "fg": "#93df5e"
  },
  "gnus-summary-normal-unread": {
    "fg": "#79D836"
  },
  "gnus-summary-low-undownloaded": {
    "fg": "cyan4"
  },
  "gnus-summary-high-undownloaded": {
    "fg": "cyan4"
  },
  "gnus-summary-normal-undownloaded": {
    "fg": "cyan4"
  },
  "gnus-summary-low-ancient": {
    "fg": "#5e5e5e"
  },
  "gnus-summary-high-ancient": {
    "fg": "#919191"
  },
  "gnus-summary-normal-ancient": {
    "fg": "#767676"
  },
  "gnus-summary-low-ticked": {
    "fg": "#6634ac"
  },
  "gnus-summary-high-ticked": {
    "fg": "#9966df"
  },
  "gnus-summary-normal-ticked": {
    "fg": "#8041D8"
  },
  "gnus-summary-cancelled": {
    "fg": "#D83441"
  },
  "gnus-summary-selected": {
    "fg": "#3679D8"
  },
  "gnus-group-mail-low": {
    "fg": "#CEDBE5"
  },
  "gnus-group-mail-low-empty": {
    "fg": "#767676"
  },
  "gnus-group-mail-3": {
    "fg": "#CEDBE5"
  },
  "gnus-group-mail-3-empty": {
    "fg": "#767676"
  },
  "gnus-group-mail-2": {
    "fg": "#CEDBE5"
  },
  "gnus-group-mail-2-empty": {
    "fg": "#767676"
  },
  "gnus-group-mail-1": {
    "fg": "#CEDBE5"
  },
  "gnus-group-mail-1-empty": {
    "fg": "#767676"
  },
  "gnus-group-news-low": {
    "fg": "#767676"
  },
  "gnus-group-news-low-empty": {
    "fg": "#767676"
  },
  "gnus-group-news-6": {
    "fg": "#CEDBE5"
  },
  "gnus-group-news-6-empty": {
    "fg": "#767676"
  },
  "gnus-group-news-5": {
    "fg": "#CEDBE5"
  },
  "gnus-group-news-5-empty": {
    "fg": "#767676"
  },
  "gnus-group-news-4": {
    "fg": "#CEDBE5"
  },
  "gnus-group-news-4-empty": {
    "fg": "#767676"
  },
  "gnus-group-news-3": {
    "fg": "#CEDBE5"
  },
  "gnus-group-news-3-empty": {
    "fg": "#767676"
  },
  "gnus-group-news-2": {
    "fg": "#CEDBE5"
  },
  "gnus-group-news-2-empty": {
    "fg": "#767676"
  },
  "gnus-group-news-1": {
    "fg": "#CEDBE5"
  },
  "gnus-group-news-1-empty": {
    "fg": "#767676"
  },
  "doc-view-svg-face": {
    "fg": "black",
    "bg": "white"
  },
  "org-habit-overdue-future-face": {
    "bg": "#431219"
  },
  "org-habit-overdue-face": {
    "bg": "#6e1c24"
  },
  "org-habit-alert-future-face": {
    "bg": "#433a19"
  },
  "org-habit-alert-face": {
    "bg": "#6e5e24"
  },
  "org-habit-ready-future-face": {
    "bg": "#122746"
  },
  "org-habit-ready-face": {
    "bg": "#1d3e70"
  },
  "org-habit-clear-future-face": {
    "bg": "#464A56"
  },
  "org-habit-clear-face": {
    "bg": "#585C6C"
  },
  "restclient-request-hook-args-face": {
    "fg": "#79D836"
  },
  "restclient-request-hook-name-face": {
    "fg": "#D8B941"
  },
  "restclient-request-hook-face": {
    "fg": "#3679D8"
  },
  "restclient-header-value-face": {
    "fg": "#79D836"
  },
  "restclient-header-name-face": {
    "fg": "#86e7d7"
  },
  "restclient-file-upload-face": {
    "fg": "#9ae168"
  },
  "restclient-url-face": {
    "fg": "#D8B941"
  },
  "restclient-method-face": {
    "fg": "#D83441"
  },
  "restclient-variable-usage-face": {
    "fg": "#3679D8"
  },
  "restclient-variable-multiline-face": {
    "fg": "#9ae168"
  },
  "restclient-variable-elisp-face": {
    "fg": "#D8B941"
  },
  "restclient-variable-string-face": {
    "fg": "#79D836"
  },
  "restclient-variable-name-face": {
    "fg": "#3679D8"
  },
  "sh-escaped-newline": {
    "fg": "#79D836"
  },
  "sh-quoted-exec": {
    "fg": "#3679D8"
  },
  "sh-heredoc": {
    "fg": "#79D836"
  },
  "treesit-explorer-anonymous-node": {
    "fg": "#767676"
  },
  "org-mode-line-clock-overrun": {
    "bg": "red"
  },
  "org-mode-line-clock": {
    "bg": "#464A56"
  },
  "org-tag-group": {
    "fg": "#9ae168"
  },
  "org-macro": {
    "fg": "#D0D0D0"
  },
  "org-latex-and-related": {
    "fg": "#D0D0D0"
  },
  "org-agenda-calendar-sexp": {
    "fg": "#CEDBE5",
    "bg": "#0D0E16"
  },
  "org-agenda-calendar-event": {
    "fg": "#CEDBE5",
    "bg": "#0D0E16"
  },
  "org-agenda-calendar-daterange": {
    "fg": "#CEDBE5",
    "bg": "#0D0E16"
  },
  "org-agenda-diary": {
    "fg": "#CEDBE5",
    "bg": "#0D0E16"
  },
  "org-agenda-current-time": {
    "fg": "#767676"
  },
  "org-time-grid": {
    "fg": "#767676"
  },
  "org-agenda-filter-regexp": {
    "bg": "#464A56"
  },
  "org-agenda-filter-effort": {
    "bg": "#464A56"
  },
  "org-agenda-filter-category": {
    "bg": "#464A56"
  },
  "org-agenda-filter-tags": {
    "bg": "#464A56"
  },
  "org-agenda-restriction-lock": {
    "bg": "#1C1C1C"
  },
  "org-upcoming-distant-deadline": {
    "fg": "#6d747d"
  },
  "org-upcoming-deadline": {
    "fg": "#a7b2bb"
  },
  "org-imminent-deadline": {
    "fg": "#D85F00"
  },
  "org-scheduled-previously": {
    "fg": "#D0D0D0"
  },
  "org-agenda-dimmed-todo-face": {
    "fg": "#767676"
  },
  "org-scheduled-today": {
    "fg": "#B2B2B2"
  },
  "org-scheduled": {
    "fg": "#CEDBE5"
  },
  "org-agenda-date-weekend": {
    "fg": "#660a81"
  },
  "org-agenda-clocking": {
    "bg": "#15233c"
  },
  "org-agenda-date-weekend-today": {
    "fg": "#cc70e7"
  },
  "org-agenda-date-today": {
    "fg": "#cc70e7"
  },
  "org-agenda-date": {
    "fg": "#AB11D8"
  },
  "org-agenda-structure-filter": {
    "fg": "#D85F00"
  },
  "org-agenda-structure-secondary": {
    "fg": "#CEDBE5"
  },
  "org-agenda-structure": {
    "fg": "#CEDBE5"
  },
  "org-clock-overlay": {
    "fg": "white",
    "bg": "SkyBlue4"
  },
  "org-verse": {
    "bg": "#040408"
  },
  "org-quote": {
    "bg": "#121212"
  },
  "org-verbatim": {
    "fg": "#79D836"
  },
  "org-inline-src-block": {
    "bg": "#040408"
  },
  "org-block-end-line": {
    "fg": "#767676",
    "bg": "#0D0E16"
  },
  "org-block-begin-line": {
    "fg": "#767676",
    "bg": "#0D0E16"
  },
  "org-block": {
    "bg": "#040408"
  },
  "org-document-info-keyword": {
    "fg": "#767676"
  },
  "org-document-info": {
    "fg": "#3679D8"
  },
  "org-document-title": {
    "fg": "#3679D8"
  },
  "org-meta-line": {
    "fg": "#9ae168"
  },
  "org-code": {
    "fg": "#D85F00",
    "bg": "#040408"
  },
  "org-formula": {
    "fg": "#36D8BD"
  },
  "org-table-header": {
    "fg": "Black",
    "bg": "LightGray"
  },
  "org-table-row": {
    "fg": "#AB11D8"
  },
  "org-table": {
    "fg": "#AB11D8"
  },
  "org-checkbox-statistics-done": {
    "fg": "#767676"
  },
  "org-checkbox-statistics-todo": {
    "fg": "#79D836"
  },
  "org-checkbox": {
    "fg": "#79D836"
  },
  "org-priority": {
    "fg": "#D83441"
  },
  "org-headline-done": {
    "fg": "#767676"
  },
  "org-headline-todo": {
    "fg": "Pink2"
  },
  "org-agenda-done": {
    "fg": "#767676"
  },
  "org-done": {
    "fg": "#767676"
  },
  "org-todo": {
    "fg": "#79D836"
  },
  "org-list-dt": {
    "fg": "#D85F00"
  },
  "org-tag": {
    "fg": "#9ae168"
  },
  "org-sexp-date": {
    "fg": "#CEDBE5"
  },
  "org-date-selected": {
    "fg": "Pink"
  },
  "org-date": {
    "fg": "#D8B941"
  },
  "org-ellipsis": {
    "fg": "#767676"
  },
  "org-footnote": {
    "fg": "#D85F00"
  },
  "org-link": {
    "fg": "#D85F00"
  },
  "org-cite-key": {
    "fg": "#6db1a1"
  },
  "org-cite": {
    "fg": "#3d9b7f"
  },
  "org-archived": {
    "fg": "#9ae168"
  },
  "org-warning": {
    "fg": "#D85F00"
  },
  "org-agenda-column-dateline": {
    "bg": "grey30"
  },
  "org-column-title": {
    "bg": "grey30"
  },
  "org-column": {
    "bg": "grey30"
  },
  "org-property-value": {
    "fg": "#9ae168"
  },
  "org-drawer": {
    "fg": "#767676"
  },
  "org-special-keyword": {
    "fg": "#9ae168"
  },
  "org-level-8": {
    "fg": "#d6e4f7"
  },
  "org-level-7": {
    "fg": "#bfa0eb"
  },
  "org-level-6": {
    "fg": "#9abceb"
  },
  "org-level-5": {
    "fg": "#9f70e1"
  },
  "org-level-4": {
    "fg": "#689ae1"
  },
  "org-level-3": {
    "fg": "#AB11D8"
  },
  "org-level-2": {
    "fg": "#8041D8"
  },
  "org-level-1": {
    "fg": "#3679D8"
  },
  "org-dispatcher-highlight": {
    "fg": "gold1",
    "bg": "gray20"
  },
  "org-hide": {
    "fg": "#0D0E16"
  },
  "outline-8": {
    "fg": "#d6e4f7"
  },
  "outline-7": {
    "fg": "#bfa0eb"
  },
  "outline-6": {
    "fg": "#9abceb"
  },
  "outline-5": {
    "fg": "#9f70e1"
  },
  "outline-4": {
    "fg": "#689ae1"
  },
  "outline-3": {
    "fg": "#AB11D8"
  },
  "outline-2": {
    "fg": "#8041D8"
  },
  "outline-1": {
    "fg": "#3679D8"
  },
  "calendar-month-header": {
    "fg": "#D8B941"
  },
  "calendar-weekend-header": {
    "fg": "#767676"
  },
  "calendar-weekday-header": {
    "fg": "#8041D8"
  },
  "holiday": {
    "bg": "chocolate4"
  },
  "diary": {
    "fg": "yellow1"
  },
  "whitespace-space-after-tab": {
    "fg": "firebrick",
    "bg": "yellow"
  },
  "whitespace-empty": {
    "bg": "#464A56"
  },
  "whitespace-missing-newline-at-eof": {
    "fg": "black",
    "bg": "#d0d040"
  },
  "whitespace-big-indent": {
    "fg": "#CEDBE5",
    "bg": "#0D0E16"
  },
  "whitespace-indentation": {
    "fg": "#CEDBE5",
    "bg": "#0D0E16"
  },
  "whitespace-space-before-tab": {
    "fg": "firebrick",
    "bg": "DarkOrange"
  },
  "whitespace-line": {
    "fg": "#D83441",
    "bg": "#0F1019"
  },
  "whitespace-trailing": {
    "bg": "#D83441"
  },
  "whitespace-newline": {
    "fg": "#585C6C"
  },
  "whitespace-tab": {
    "fg": "#585C6C",
    "bg": "#464A56"
  },
  "whitespace-hspace": {
    "fg": "darkgray",
    "bg": "grey24"
  },
  "whitespace-space": {
    "fg": "#585C6C"
  },
  "helm-swoop-line-number-face": {
    "fg": "#999999"
  },
  "helm-swoop-target-word-face": {
    "fg": "#79D836"
  },
  "helm-swoop-target-line-block-face": {
    "fg": "#D8B941"
  },
  "helm-swoop-target-line-face": {
    "fg": "#D85F00"
  },
  "helm-M-x-short-doc": {
    "fg": "DimGray"
  },
  "helm-command-debug-active": {
    "fg": "#D85F00"
  },
  "helm-command-minor-active-mode": {
    "fg": "#3679D8"
  },
  "helm-command-major-active-mode": {
    "fg": "#3679D8"
  },
  "helm-M-x-key": {
    "fg": "orange"
  },
  "helm-lisp-completion-info": {
    "fg": "red"
  },
  "helm-lisp-show-completion": {
    "bg": "DarkSlateGray"
  },
  "edebug-disabled-breakpoint": {
    "bg": "#335533"
  },
  "edebug-enabled-breakpoint": {
    "fg": "#0F1019",
    "bg": "#D85F00"
  },
  "helm-descbinds-binding": {
    "fg": "#D85F00"
  },
  "helm-completions-key-binding": {
    "fg": "#8041D8"
  },
  "helm-completions-annotations": {
    "fg": "#86e7d7"
  },
  "helm-completions-detailed": {
    "fg": "#D85F00"
  },
  "helm-completion-invalid": {
    "fg": "#86e7d7"
  },
  "helm-time-zone-home": {
    "fg": "red"
  },
  "helm-time-zone-current": {
    "fg": "green"
  },
  "helm-ff-rsync-progress-svg": {
    "fg": "white",
    "bg": "black"
  },
  "helm-ff-rsync-progress-3": {
    "bg": "white"
  },
  "helm-ff-rsync-progress-2": {
    "bg": "orange"
  },
  "helm-ff-rsync-progress-1": {
    "fg": "black",
    "bg": "CadetBlue"
  },
  "helm-ff-rsync-progress": {
    "fg": "#D85F00"
  },
  "helm-delete-async-message": {
    "fg": "yellow"
  },
  "helm-history-remote": {
    "fg": "IndianRed1"
  },
  "helm-history-deleted": {
    "fg": "black",
    "bg": "red"
  },
  "helm-ff-backup-file": {
    "fg": "DimGray"
  },
  "helm-ff-file-extension": {
    "fg": "magenta"
  },
  "helm-ff-pipe": {
    "fg": "yellow",
    "bg": "black"
  },
  "helm-ff-socket": {
    "fg": "DeepPink"
  },
  "helm-ff-dirs": {
    "fg": "#D8B941"
  },
  "helm-ff-truename": {
    "fg": "#79D836"
  },
  "helm-ff-nofile": {
    "fg": "#CEDBE5"
  },
  "helm-ff-file": {
    "fg": "#CEDBE5"
  },
  "helm-ff-denied": {
    "fg": "red",
    "bg": "black"
  },
  "helm-ff-invalid-symlink": {
    "fg": "black",
    "bg": "red"
  },
  "helm-ff-symlink": {
    "fg": "#767676"
  },
  "helm-ff-dotted-symlink-directory": {
    "fg": "DarkOrange",
    "bg": "DimGray"
  },
  "helm-ff-dotted-directory": {
    "fg": "#767676"
  },
  "helm-ff-directory": {
    "fg": "#86e7d7"
  },
  "helm-ff-suid": {
    "fg": "white",
    "bg": "red"
  },
  "helm-ff-executable": {
    "fg": "#D0D0D0"
  },
  "helm-ff-prefix": {
    "fg": "#D83441"
  },
  "image-dired-thumb-flagged": {
    "bg": "Pink"
  },
  "image-dired-thumb-mark": {
    "bg": "DarkOrange"
  },
  "image-dired-thumb-header-image-count": {
    "bg": "#464A56"
  },
  "image-dired-thumb-header-file-size": {
    "fg": "cadet blue"
  },
  "image-dired-thumb-header-directory-name": {
    "bg": "#464A56"
  },
  "shell-highlight-undef-alias-face": {
    "fg": "#86e7d7"
  },
  "shell-highlight-undef-undefined-face": {
    "fg": "#D85F00"
  },
  "shell-highlight-undef-defined-face": {
    "fg": "#D8B941"
  },
  "helm-buffer-archive": {
    "fg": "gold"
  },
  "helm-buffer-file": {
    "fg": "#3679D8"
  },
  "helm-buffer-directory": {
    "fg": "DarkRed",
    "bg": "LightGray"
  },
  "helm-buffer-process": {
    "fg": "sienna3"
  },
  "helm-buffer-size": {
    "fg": "RosyBrown"
  },
  "helm-indirect-buffer": {
    "fg": "DimGray",
    "bg": "black"
  },
  "helm-no-file-buffer-modified": {
    "fg": "orange",
    "bg": "black"
  },
  "helm-buffer-modified": {
    "fg": "#767676"
  },
  "helm-buffer-not-saved": {
    "fg": "IndianRed2"
  },
  "helm-buffer-saved-out": {
    "fg": "red",
    "bg": "black"
  },
  "all-the-icons-dsilver": {
    "fg": "#838383"
  },
  "all-the-icons-lsilver": {
    "fg": "#d5d5d5"
  },
  "all-the-icons-silver": {
    "fg": "#b3b3b3"
  },
  "all-the-icons-dpink": {
    "fg": "#dd525d"
  },
  "all-the-icons-lpink": {
    "fg": "#eda3a9"
  },
  "all-the-icons-pink": {
    "fg": "#e57b83"
  },
  "all-the-icons-dcyan": {
    "fg": "#092D27"
  },
  "all-the-icons-lcyan": {
    "fg": "#72e3d0"
  },
  "all-the-icons-cyan-alt": {
    "fg": "#36D8BD"
  },
  "all-the-icons-cyan": {
    "fg": "#36D8BD"
  },
  "all-the-icons-dorange": {
    "fg": "#974200"
  },
  "all-the-icons-lorange": {
    "fg": "#e38f4c"
  },
  "all-the-icons-orange": {
    "fg": "#D85F00"
  },
  "all-the-icons-dpurple": {
    "fg": "#770b97"
  },
  "all-the-icons-lpurple": {
    "fg": "#c458e3"
  },
  "all-the-icons-purple-alt": {
    "fg": "#7d6684"
  },
  "all-the-icons-purple": {
    "fg": "#AB11D8"
  },
  "all-the-icons-dmaroon": {
    "fg": "#592d97"
  },
  "all-the-icons-lmaroon": {
    "fg": "#a67ae3"
  },
  "all-the-icons-maroon": {
    "fg": "#8041D8"
  },
  "all-the-icons-dblue": {
    "fg": "#2D9574"
  },
  "all-the-icons-lblue": {
    "fg": "#72a1e3"
  },
  "all-the-icons-blue-alt": {
    "fg": "#2D9574"
  },
  "all-the-icons-blue": {
    "fg": "#3679D8"
  },
  "all-the-icons-dyellow": {
    "fg": "#97812d"
  },
  "all-the-icons-lyellow": {
    "fg": "#e3ce7a"
  },
  "all-the-icons-yellow": {
    "fg": "#D8B941"
  },
  "all-the-icons-dgreen": {
    "fg": "#549725"
  },
  "all-the-icons-lgreen": {
    "fg": "#a1e372"
  },
  "all-the-icons-green": {
    "fg": "#79D836"
  },
  "all-the-icons-red-alt": {
    "fg": "#846c6e"
  },
  "all-the-icons-dred": {
    "fg": "#97242d"
  },
  "all-the-icons-lred": {
    "fg": "#e3707a"
  },
  "all-the-icons-red": {
    "fg": "#D83441"
  },
  "helm-resume-need-update": {
    "bg": "red"
  },
  "helm-moccur-buffer": {
    "fg": "#D85F00"
  },
  "helm-etags-file": {
    "fg": "Lightgoldenrod4"
  },
  "helm-locate-finish": {
    "fg": "Green"
  },
  "helm-grep-cmd-line": {
    "fg": "#3679D8"
  },
  "helm-grep-finish": {
    "fg": "#79D836"
  },
  "helm-grep-lineno": {
    "fg": "#767676"
  },
  "helm-grep-file": {
    "fg": "#36D8BD"
  },
  "helm-grep-match": {
    "fg": "#D85F00"
  },
  "helm-tooltip": {
    "fg": "black",
    "bg": "goldenrod"
  },
  "helm-match-item": {
    "fg": "#D0D0D0",
    "bg": "#974200"
  },
  "helm-selection-line": {
    "fg": "#0F1019",
    "bg": "#D85F00"
  },
  "helm-helper": {
    "bg": "#464A56"
  },
  "helm-dim-prompt": {
    "fg": "DimGray"
  },
  "helm-mark-prefix": {
    "fg": "#CEDBE5",
    "bg": "#0D0E16"
  },
  "helm-eob-line": {
    "fg": "#CEDBE5",
    "bg": "#0D0E16"
  },
  "helm-minibuffer-prompt": {
    "fg": "#D85F00"
  },
  "helm-header-line-left-margin": {
    "fg": "black",
    "bg": "yellow"
  },
  "helm-match": {
    "fg": "#D85F00"
  },
  "helm-prefarg": {
    "fg": "green"
  },
  "helm-separator": {
    "fg": "red"
  },
  "helm-selection": {
    "bg": "#0C213E"
  },
  "helm-candidate-number-suspended": {
    "fg": "black",
    "bg": "yellow"
  },
  "helm-candidate-number": {
    "fg": "black",
    "bg": "yellow"
  },
  "helm-header": {
    "bg": "#464A56"
  },
  "helm-visible-mark": {
    "fg": "#0F1019",
    "bg": "#D85F00"
  },
  "helm-source-header": {
    "fg": "#D83441",
    "bg": "#1E1E33"
  },
  "company-template-field": {
    "fg": "#79D836",
    "bg": "#0F1019"
  },
  "company-echo-common": {
    "fg": "firebrick1"
  },
  "company-preview-search": {
    "fg": "#0D0E16",
    "bg": "#D85F00"
  },
  "company-preview-common": {
    "fg": "#D85F00",
    "bg": "#464A56"
  },
  "company-preview": {
    "fg": "#767676"
  },
  "company-tooltip-scrollbar-track": {
    "fg": "#CEDBE5",
    "bg": "#040408"
  },
  "company-tooltip-scrollbar-thumb": {
    "bg": "#D85F00"
  },
  "company-tooltip-quick-access-selection": {
    "fg": "#AB11D8"
  },
  "company-tooltip-quick-access": {
    "fg": "#AB11D8"
  },
  "company-tooltip-annotation-selection": {
    "fg": "#AB11D8"
  },
  "company-tooltip-annotation": {
    "fg": "#AB11D8"
  },
  "company-tooltip-common-selection": {
    "fg": "#D85F00"
  },
  "company-tooltip-common": {
    "fg": "#D85F00"
  },
  "company-tooltip-mouse": {
    "fg": "#0D0E16",
    "bg": "#8041D8"
  },
  "company-tooltip-search-selection": {
    "bg": "#09182e"
  },
  "company-tooltip-search": {
    "fg": "#0D0E16",
    "bg": "#D85F00"
  },
  "company-tooltip-selection": {
    "bg": "#0C213E"
  },
  "company-tooltip": {
    "fg": "#CEDBE5",
    "bg": "#040408"
  },
  "xref-match": {
    "fg": "#79D836",
    "bg": "#0F1019"
  },
  "xref-line-number": {
    "fg": "#D85F00"
  },
  "xref-file-header": {
    "fg": "#79D836"
  },
  "eval-sexp-fu-flash-error": {
    "fg": "red"
  },
  "eval-sexp-fu-flash": {
    "bg": "slate blue"
  },
  "vc-git-log-edit-summary-max-warning": {
    "fg": "#D83441"
  },
  "vc-git-log-edit-summary-target-warning": {
    "fg": "#D85F00"
  },
  "copilot-overlay-face": {
    "fg": "#767676"
  },
  "flycheck-error-list-checker-name": {
    "fg": "#D8B941"
  },
  "flycheck-error-list-id-with-explainer": {
    "fg": "#3679D8"
  },
  "flycheck-error-list-id": {
    "fg": "#3679D8"
  },
  "flycheck-error-list-info": {
    "fg": "#79D836"
  },
  "flycheck-error-list-warning": {
    "fg": "#D85F00"
  },
  "flycheck-error-list-error": {
    "fg": "#D83441"
  },
  "flycheck-fringe-info": {
    "fg": "#79D836",
    "bg": "#0D0E16"
  },
  "flycheck-fringe-warning": {
    "fg": "#D85F00",
    "bg": "#0D0E16"
  },
  "flycheck-fringe-error": {
    "fg": "#D83441",
    "bg": "#0D0E16"
  },
  "highlight-numbers-number": {
    "fg": "#D85F00"
  },
  "rainbow-delimiters-depth-1-face": {
    "fg": "#3679D8"
  },
  "rainbow-delimiters-depth-2-face": {
    "fg": "#8041D8"
  },
  "rainbow-delimiters-depth-3-face": {
    "fg": "#79D836"
  },
  "rainbow-delimiters-depth-4-face": {
    "fg": "#AB11D8"
  },
  "rainbow-delimiters-depth-5-face": {
    "fg": "#2D9574"
  },
  "rainbow-delimiters-depth-6-face": {
    "fg": "#3679D8"
  },
  "rainbow-delimiters-depth-7-face": {
    "fg": "#8041D8"
  },
  "rainbow-delimiters-depth-8-face": {
    "fg": "#79D836"
  },
  "rainbow-delimiters-depth-9-face": {
    "fg": "#AB11D8"
  },
  "rainbow-delimiters-mismatched-face": {
    "fg": "#D83441"
  },
  "rainbow-delimiters-unmatched-face": {
    "fg": "#D83441"
  },
  "rainbow-delimiters-base-error-face": {
    "fg": "#D83441",
    "bg": "#0D0E16"
  },
  "rainbow-delimiters-base-face": {
    "fg": "#CEDBE5",
    "bg": "#0D0E16"
  },
  "sp-show-pair-enclosing": {
    "fg": "#0F1019",
    "bg": "#D85F00"
  },
  "sp-show-pair-mismatch-face": {
    "fg": "#0F1019",
    "bg": "#D83441"
  },
  "sp-show-pair-match-face": {
    "fg": "#D83441",
    "bg": "#0F1019"
  },
  "sp-wrap-tag-overlay-face": {
    "fg": "#D0D0D0",
    "bg": "#974200"
  },
  "sp-wrap-overlay-closing-pair": {
    "fg": "red",
    "bg": "#974200"
  },
  "sp-wrap-overlay-opening-pair": {
    "fg": "green",
    "bg": "#974200"
  },
  "sp-wrap-overlay-face": {
    "fg": "#D0D0D0",
    "bg": "#974200"
  },
  "sp-pair-overlay-face": {
    "fg": "#D0D0D0",
    "bg": "#974200"
  },
  "yas-field-highlight-face": {
    "fg": "#79D836",
    "bg": "#0F1019"
  },
  "spaceline-python-venv": {
    "fg": "#8041D8"
  },
  "spaceline-flycheck-info": {
    "fg": "#79D836"
  },
  "spaceline-flycheck-warning": {
    "fg": "#D85F00"
  },
  "spaceline-flycheck-error": {
    "fg": "#D83441"
  },
  "spaceline-read-only": {
    "fg": "#3E3D31",
    "bg": "plum3"
  },
  "spaceline-modified": {
    "bg": "#D8B941"
  },
  "spaceline-unmodified": {
    "bg": "#8041D8"
  },
  "spaceline-evil-motion": {
    "bg": "#8041D8"
  },
  "spaceline-evil-visual": {
    "bg": "#767676"
  },
  "spaceline-evil-replace": {
    "bg": "#D85F00"
  },
  "spaceline-evil-emacs": {
    "bg": "#36D8BD"
  },
  "spaceline-evil-insert": {
    "bg": "#79D836"
  },
  "spaceline-evil-normal": {
    "bg": "#3679D8"
  },
  "spaceline-highlight-face": {
    "bg": "#D85F00"
  },
  "powerline-inactive2": {
    "fg": "#B2B2B2",
    "bg": "#27273b"
  },
  "powerline-inactive1": {
    "fg": "#B2B2B2",
    "bg": "#222237"
  },
  "powerline-inactive0": {
    "fg": "#B2B2B2",
    "bg": "#1E1E33"
  },
  "powerline-active2": {
    "fg": "#D0D0D0",
    "bg": "#202128"
  },
  "powerline-active1": {
    "bg": "#13141b"
  },
  "powerline-active0": {
    "bg": "#0D0E16"
  },
  "diff-hl-change": {
    "fg": "#D8B941",
    "bg": "#D8B941"
  },
  "diff-hl-delete": {
    "fg": "#D83441",
    "bg": "#D83441"
  },
  "diff-hl-insert": {
    "fg": "#79D836",
    "bg": "#79D836"
  },
  "log-view-commit-body": {
    "fg": "#767676"
  },
  "log-edit-unknown-header": {
    "fg": "#767676"
  },
  "log-edit-header": {
    "fg": "#D83441"
  },
  "log-edit-summary": {
    "fg": "#D8B941"
  },
  "message-mml": {
    "fg": "#767676"
  },
  "message-cited-text-4": {
    "fg": "#79D836"
  },
  "message-cited-text-3": {
    "fg": "#79D836"
  },
  "message-cited-text-2": {
    "fg": "#8041D8"
  },
  "message-cited-text-1": {
    "fg": "#AB11D8"
  },
  "message-separator": {
    "fg": "#767676"
  },
  "message-header-xheader": {
    "fg": "#9ae168"
  },
  "message-header-name": {
    "fg": "#79D836"
  },
  "message-header-other": {
    "fg": "#AB11D8"
  },
  "message-header-newsgroups": {
    "fg": "#D8B941"
  },
  "message-header-subject": {
    "fg": "#D85F00"
  },
  "message-header-cc": {
    "fg": "#b75000"
  },
  "message-header-to": {
    "fg": "#D85F00"
  },
  "epa-field-body": {
    "fg": "turquoise"
  },
  "epa-field-name": {
    "fg": "PaleTurquoise"
  },
  "epa-mark": {
    "fg": "orange"
  },
  "epa-string": {
    "fg": "lightyellow"
  },
  "epa-validity-medium": {
    "fg": "PaleTurquoise"
  },
  "epa-validity-high": {
    "fg": "PaleTurquoise"
  },
  "mm-command-output": {
    "fg": "ForestGreen"
  },
  "change-log-acknowledgment": {
    "fg": "#767676"
  },
  "change-log-function": {
    "fg": "#86e7d7"
  },
  "change-log-conditionals": {
    "fg": "#86e7d7"
  },
  "change-log-list": {
    "fg": "#D83441"
  },
  "change-log-file": {
    "fg": "#D8B941"
  },
  "change-log-email": {
    "fg": "#86e7d7"
  },
  "change-log-name": {
    "fg": "#8041D8"
  },
  "change-log-date": {
    "fg": "#79D836"
  },
  "vc-dir-status-ignored": {
    "fg": "#767676"
  },
  "vc-dir-status-up-to-date": {
    "fg": "#3679D8"
  },
  "vc-dir-status-edited": {
    "fg": "#86e7d7"
  },
  "vc-dir-status-warning": {
    "fg": "#D85F00"
  },
  "vc-dir-mark-indicator": {
    "fg": "#3679D8"
  },
  "vc-dir-file": {
    "fg": "#D8B941"
  },
  "vc-dir-directory": {
    "fg": "#767676"
  },
  "vc-dir-header-value": {
    "fg": "#86e7d7"
  },
  "vc-dir-header": {
    "fg": "#3679D8"
  },
  "diff-refine-added": {
    "fg": "#79D836",
    "bg": "#040408"
  },
  "diff-refine-removed": {
    "fg": "#D83441",
    "bg": "#464A56"
  },
  "diff-refine-changed": {
    "fg": "#AB11D8"
  },
  "diff-error": {
    "fg": "red",
    "bg": "black"
  },
  "diff-nonexistent": {
    "fg": "#3679D8"
  },
  "diff-context": {
    "fg": "#b5c0c9"
  },
  "diff-function": {
    "fg": "#36D8BD"
  },
  "diff-indicator-changed": {
    "fg": "#D8B941"
  },
  "diff-indicator-added": {
    "fg": "#79D836"
  },
  "diff-indicator-removed": {
    "fg": "#79D836"
  },
  "diff-changed": {
    "fg": "#AB11D8"
  },
  "diff-changed-unspecified": {
    "fg": "#AB11D8",
    "bg": "grey20"
  },
  "diff-added": {
    "fg": "#79D836",
    "bg": "#040408"
  },
  "diff-removed": {
    "fg": "#D83441",
    "bg": "#464A56"
  },
  "diff-hunk-header": {
    "fg": "#AB11D8"
  },
  "diff-index": {
    "fg": "#3679D8"
  },
  "diff-file-header": {
    "fg": "#3679D8"
  },
  "diff-header": {
    "fg": "#36D8BD"
  },
  "grep-heading": {
    "fg": "#79D836"
  },
  "winum-face": {
    "fg": "#D85F00"
  },
  "imenu-list-entry-subalist-face-3": {
    "fg": "sandy brown"
  },
  "imenu-list-entry-face-3": {
    "fg": "sandy brown"
  },
  "imenu-list-entry-subalist-face-2": {
    "fg": "#D8B941"
  },
  "imenu-list-entry-face-2": {
    "fg": "#D8B941"
  },
  "imenu-list-entry-subalist-face-1": {
    "fg": "#79D836"
  },
  "imenu-list-entry-face-1": {
    "fg": "#79D836"
  },
  "imenu-list-entry-subalist-face-0": {
    "fg": "#D85F00"
  },
  "imenu-list-entry-face-0": {
    "fg": "#D85F00"
  },
  "hs-ellipsis": {
    "fg": "#CEDBE5",
    "bg": "#0D0E16"
  },
  "ibuffer-locked-buffer": {
    "fg": "RosyBrown"
  },
  "dired-ignored": {
    "fg": "#767676"
  },
  "dired-special": {
    "fg": "#86e7d7"
  },
  "dired-broken-symlink": {
    "fg": "yellow1",
    "bg": "red1"
  },
  "dired-symlink": {
    "fg": "#36D8BD"
  },
  "dired-directory": {
    "fg": "#3679D8"
  },
  "dired-set-id": {
    "fg": "#D85F00"
  },
  "dired-perm-write": {
    "fg": "#CEDBE5"
  },
  "dired-warning": {
    "fg": "#D85F00"
  },
  "dired-flagged": {
    "fg": "#D83441"
  },
  "dired-marked": {
    "fg": "#8041D8"
  },
  "dired-mark": {
    "fg": "#D85F00"
  },
  "dired-header": {
    "fg": "#3679D8"
  },
  "vhl/default-face": {
    "bg": "#767676"
  },
  "symbol-overlay-face-8": {
    "bg": "#153637"
  },
  "symbol-overlay-face-7": {
    "bg": "#385e22"
  },
  "symbol-overlay-face-6": {
    "bg": "#2f1d50"
  },
  "symbol-overlay-face-5": {
    "bg": "#491922"
  },
  "symbol-overlay-face-4": {
    "bg": "#49260f"
  },
  "symbol-overlay-face-3": {
    "bg": "#494122"
  },
  "symbol-overlay-face-2": {
    "bg": "#4c0f63"
  },
  "symbol-overlay-face-1": {
    "bg": "#1d3863"
  },
  "symbol-overlay-default-face": {
    "bg": "#343447"
  },
  "persp-face-lighter-default": {
    "fg": "#D85F00"
  },
  "persp-face-lighter-nil-persp": {
    "fg": "#767676"
  },
  "persp-face-lighter-buffer-not-in-persp": {
    "fg": "#9ae168"
  },
  "page-break-lines": {
    "fg": "#767676"
  },
  "c-annotation-face": {
    "fg": "#8041D8"
  },
  "hl-todo-flymake-type": {
    "fg": "#D83441"
  },
  "hl-todo": {
    "fg": "#D83441"
  },
  "eyebrowse-mode-line-active": {
    "fg": "#D85F00"
  },
  "anzu-replace-to": {
    "fg": "#79D836",
    "bg": "#0F1019"
  },
  "anzu-match-3": {
    "fg": "black",
    "bg": "aquamarine"
  },
  "anzu-match-2": {
    "fg": "black",
    "bg": "yellow"
  },
  "anzu-match-1": {
    "fg": "black",
    "bg": "limegreen"
  },
  "anzu-replace-highlight": {
    "fg": "#D83441",
    "bg": "#0F1019"
  },
  "anzu-mode-line-no-match": {
    "fg": "magenta"
  },
  "anzu-mode-line": {
    "fg": "magenta"
  },
  "info-variable-ref-item": {
    "fg": "Orange",
    "bg": "gray12"
  },
  "info-user-option-ref-item": {
    "fg": "Red",
    "bg": "gray12"
  },
  "info-syntax-class-item": {
    "fg": "#FFFF9B9BFFFF",
    "bg": "gray12"
  },
  "info-special-form-ref-item": {
    "fg": "Green",
    "bg": "gray12"
  },
  "info-reference-item": {
    "bg": "gray12"
  },
  "info-macro-ref-item": {
    "fg": "Yellow",
    "bg": "gray12"
  },
  "info-function-ref-item": {
    "fg": "#4D4DDDDDDDDD",
    "bg": "gray12"
  },
  "info-constant-ref-item": {
    "fg": "DeepPink",
    "bg": "gray12"
  },
  "info-command-ref-item": {
    "fg": "#7474FFFF7474",
    "bg": "gray12"
  },
  "info-isolated-backquote": {
    "fg": "Green",
    "bg": "Magenta"
  },
  "info-isolated-quote": {
    "fg": "Green",
    "bg": "#46462C2C1111"
  },
  "info-string": {
    "fg": "Orange"
  },
  "info-quoted-name": {
    "fg": "#6B6BFFFF2C2C"
  },
  "info-menu": {
    "fg": "Yellow"
  },
  "info-homoglyph": {
    "fg": "cyan"
  },
  "info-file": {
    "fg": "Yellow",
    "bg": "gray12"
  },
  "info-indented-text": {
    "fg": "DarkBlue"
  },
  "info-double-quoted-name": {
    "fg": "Cyan"
  },
  "info-custom-delimited": {
    "fg": "Red"
  },
  "which-key-docstring-face": {
    "fg": "#767676"
  },
  "which-key-special-key-face": {
    "fg": "#79D836"
  },
  "which-key-group-description-face": {
    "fg": "#AB11D8"
  },
  "which-key-highlighted-command-face": {
    "fg": "#3679D8",
    "bg": "#D85F00"
  },
  "which-key-local-map-description-face": {
    "fg": "#8041D8"
  },
  "which-key-command-description-face": {
    "fg": "#3679D8"
  },
  "which-key-note-face": {
    "fg": "#767676"
  },
  "which-key-separator-face": {
    "fg": "#767676"
  },
  "which-key-key-face": {
    "fg": "#79D836"
  },
  "hydra-face-teal": {
    "fg": "#2D9574"
  },
  "hydra-face-pink": {
    "fg": "#AB11D8"
  },
  "hydra-face-amaranth": {
    "fg": "#8041D8"
  },
  "hydra-face-blue": {
    "fg": "#3679D8"
  },
  "hydra-face-red": {
    "fg": "#D83441"
  },
  "lv-separator": {
    "bg": "grey30"
  },
  "spacemacs-iedit-insert-face": {
    "bg": "firebrick1"
  },
  "spacemacs-iedit-face": {
    "bg": "firebrick1"
  },
  "spacemacs-lisp-face": {
    "bg": "HotPink1"
  },
  "spacemacs-motion-face": {
    "bg": "plum3"
  },
  "spacemacs-visual-face": {
    "bg": "SteelBlue3"
  },
  "spacemacs-evilified-face": {
    "bg": "LightGoldenrod3"
  },
  "spacemacs-replace-face": {
    "bg": "chocolate"
  },
  "spacemacs-hybrid-face": {
    "bg": "SkyBlue2"
  },
  "spacemacs-emacs-face": {
    "bg": "SkyBlue2"
  },
  "spacemacs-insert-face": {
    "bg": "chartreuse3"
  },
  "spacemacs-normal-face": {
    "bg": "DarkGoldenrod2"
  },
  "rectangle-preview": {
    "bg": "#1E1E33"
  },
  "evil-ex-substitute-replacement": {
    "fg": "#79D836",
    "bg": "#0F1019"
  },
  "evil-ex-substitute-matches": {
    "fg": "#D83441",
    "bg": "#0F1019"
  },
  "evil-ex-lazy-highlight": {
    "fg": "#D0D0D0",
    "bg": "#974200"
  },
  "evil-ex-search": {
    "fg": "#0F1019",
    "bg": "#D85F00"
  },
  "evil-ex-info": {
    "fg": "#D83441"
  },
  "edmacro-label": {
    "fg": "light blue"
  },
  "kmacro-menu-marked": {
    "fg": "#D85F00"
  },
  "kmacro-menu-flagged": {
    "fg": "#D83441"
  },
  "kmacro-menu-mark": {
    "fg": "#8041D8"
  },
  "info-index-match": {
    "fg": "#79D836",
    "bg": "#0F1019"
  },
  "info-header-node": {
    "fg": "white"
  },
  "info-header-xref": {
    "fg": "#D85F00"
  },
  "info-xref-visited": {
    "fg": "violet"
  },
  "info-xref": {
    "fg": "#D85F00"
  },
  "info-menu-star": {
    "fg": "red1"
  },
  "info-node": {
    "fg": "white"
  },
  "hl-line": {
    "bg": "#040408"
  },
  "spacemacs-helm-navigation-ts-face": {
    "fg": "black",
    "bg": "red"
  },
  "compilation-column-number": {
    "fg": "#767676"
  },
  "compilation-line-number": {
    "fg": "#D85F00"
  },
  "compilation-mode-line-exit": {
    "fg": "#79D836"
  },
  "compilation-mode-line-run": {
    "fg": "#D85F00"
  },
  "compilation-mode-line-fail": {
    "fg": "#D83441"
  },
  "compilation-info": {
    "fg": "#79D836"
  },
  "compilation-warning": {
    "fg": "#D85F00"
  },
  "compilation-error": {
    "fg": "#D83441"
  },
  "comint-highlight-prompt": {
    "fg": "#D85F00"
  },
  "ansi-color-bright-white": {
    "fg": "#D0D0D0",
    "bg": "#D0D0D0"
  },
  "ansi-color-bright-cyan": {
    "fg": "#54ddc6",
    "bg": "#54ddc6"
  },
  "ansi-color-bright-magenta": {
    "fg": "#935ddd",
    "bg": "#935ddd"
  },
  "ansi-color-bright-blue": {
    "fg": "#548ddd",
    "bg": "#548ddd"
  },
  "ansi-color-bright-yellow": {
    "fg": "#ddc35d",
    "bg": "#ddc35d"
  },
  "ansi-color-bright-green": {
    "fg": "#8ddd54",
    "bg": "#8ddd54"
  },
  "ansi-color-bright-red": {
    "fg": "#dd525d",
    "bg": "#dd525d"
  },
  "ansi-color-bright-black": {
    "fg": "#959EA5",
    "bg": "#959EA5"
  },
  "ansi-color-white": {
    "fg": "#CEDBE5",
    "bg": "#CEDBE5"
  },
  "ansi-color-cyan": {
    "fg": "#36D8BD",
    "bg": "#36D8BD"
  },
  "ansi-color-magenta": {
    "fg": "#8041D8",
    "bg": "#8041D8"
  },
  "ansi-color-blue": {
    "fg": "#3679D8",
    "bg": "#3679D8"
  },
  "ansi-color-yellow": {
    "fg": "#D8B941",
    "bg": "#D8B941"
  },
  "ansi-color-green": {
    "fg": "#79D836",
    "bg": "#79D836"
  },
  "ansi-color-red": {
    "fg": "#D83441",
    "bg": "#D83441"
  },
  "ansi-color-black": {
    "fg": "#0D0E16",
    "bg": "#0D0E16"
  },
  "spacemacs-transient-state-title-face": {
    "bg": "#464A56"
  },
  "spacemacs-micro-state-binding-face": {
    "fg": "#D83441"
  },
  "spacemacs-micro-state-header-face": {
    "fg": "black",
    "bg": "DarkGoldenrod2"
  },
  "org-kbd": {
    "fg": "black",
    "bg": "LemonChiffon1"
  },
  "spacemacs-mode-line-new-version-lighter-success-face": {
    "fg": "#79D836"
  },
  "spacemacs-mode-line-new-version-lighter-warning-face": {
    "fg": "#D85F00"
  },
  "spacemacs-mode-line-new-version-lighter-error-face": {
    "fg": "#D83441"
  },
  "package-status-avail-obso": {
    "fg": "#D83441"
  },
  "package-status-incompat": {
    "fg": "#D83441"
  },
  "package-status-unsigned": {
    "fg": "#D85F00"
  },
  "package-status-dependency": {
    "fg": "#767676"
  },
  "package-status-from-source": {
    "fg": "#3679D8"
  },
  "package-status-installed": {
    "fg": "#767676"
  },
  "package-status-disabled": {
    "fg": "#D85F00"
  },
  "package-status-held": {
    "fg": "#8041D8"
  },
  "package-status-new": {
    "fg": "#CEDBE5",
    "bg": "#0D0E16"
  },
  "package-status-available": {
    "fg": "#CEDBE5",
    "bg": "#0D0E16"
  },
  "package-status-external": {
    "fg": "#3679D8"
  },
  "package-status-built-in": {
    "fg": "#3679D8"
  },
  "package-description": {
    "fg": "#CEDBE5",
    "bg": "#0D0E16"
  },
  "package-name": {
    "fg": "#D85F00"
  },
  "package-help-section-name": {
    "fg": "#D8B941"
  },
  "browse-url-button": {
    "fg": "#D85F00"
  },
  "custom-group-subtitle": {
    "fg": "#D83441"
  },
  "custom-group-tag": {
    "fg": "#AB11D8"
  },
  "custom-group-tag-1": {
    "fg": "#3679D8"
  },
  "custom-face-tag": {
    "fg": "#8041D8"
  },
  "custom-visibility": {
    "fg": "#3679D8"
  },
  "custom-variable-button": {
    "fg": "#79D836"
  },
  "custom-variable-tag": {
    "fg": "#8041D8"
  },
  "custom-variable-obsolete": {
    "fg": "#767676",
    "bg": "#0D0E16"
  },
  "custom-comment-tag": {
    "fg": "#767676"
  },
  "custom-comment": {
    "fg": "#CEDBE5",
    "bg": "#1E1E33"
  },
  "custom-link": {
    "fg": "#D85F00"
  },
  "custom-state": {
    "fg": "#79D836",
    "bg": "#22361c"
  },
  "custom-button-pressed-unraised": {
    "fg": "#0D0E16",
    "bg": "#AB11D8"
  },
  "custom-button-pressed": {
    "fg": "#0D0E16",
    "bg": "#3679D8"
  },
  "custom-button-unraised": {
    "fg": "#AB11D8",
    "bg": "#0D0E16"
  },
  "custom-button-mouse": {
    "fg": "#0D0E16",
    "bg": "#3679D8"
  },
  "custom-button": {
    "fg": "#3679D8",
    "bg": "#0D0E16"
  },
  "custom-saved": {
    "fg": "#79D836",
    "bg": "#22361c"
  },
  "custom-themed": {
    "fg": "#D8B941",
    "bg": "#0D0E16"
  },
  "custom-changed": {
    "fg": "#3679D8",
    "bg": "#0D0E16"
  },
  "custom-set": {
    "fg": "#D8B941",
    "bg": "#0D0E16"
  },
  "custom-modified": {
    "fg": "#3679D8",
    "bg": "#15233c"
  },
  "custom-rogue": {
    "fg": "pink",
    "bg": "black"
  },
  "custom-invalid": {
    "fg": "#D83441",
    "bg": "#35151e"
  },
  "icon-button": {
    "fg": "black",
    "bg": "#808080"
  },
  "widget-button-pressed": {
    "fg": "#D83441"
  },
  "widget-unselected": {
    "fg": "#767676"
  },
  "widget-inactive": {
    "fg": "#767676"
  },
  "widget-single-line-field": {
    "bg": "#464A56"
  },
  "widget-field": {
    "bg": "#464A56"
  },
  "widget-documentation": {
    "fg": "#79D836"
  },
  "tooltip": {
    "fg": "#CEDBE5",
    "bg": "#040408"
  },
  "elisp-shorthand-font-lock-face": {
    "fg": "cyan"
  },
  "match": {
    "fg": "#79D836",
    "bg": "#0F1019"
  },
  "query-replace": {
    "fg": "#D0D0D0",
    "bg": "#974200"
  },
  "tab-bar-tab-highlight": {
    "fg": "black",
    "bg": "grey85"
  },
  "tab-bar-tab-ungrouped": {
    "fg": "#767676",
    "bg": "#040408"
  },
  "tab-bar-tab-group-inactive": {
    "fg": "#767676",
    "bg": "#040408"
  },
  "tab-bar-tab-group-current": {
    "fg": "#CEDBE5",
    "bg": "#0D0E16"
  },
  "tab-bar-tab-inactive": {
    "fg": "#E5F4FF",
    "bg": "#040408"
  },
  "tab-bar-tab": {
    "fg": "#CEDBE5",
    "bg": "#0D0E16"
  },
  "file-name-shadow": {
    "fg": "#767676"
  },
  "isearch-group-2": {
    "fg": "brown4",
    "bg": "palevioletred3"
  },
  "isearch-group-1": {
    "fg": "brown4",
    "bg": "palevioletred1"
  },
  "lazy-highlight": {
    "fg": "#D0D0D0",
    "bg": "#974200"
  },
  "isearch-fail": {
    "fg": "#0F1019",
    "bg": "#D83441"
  },
  "isearch": {
    "fg": "#D0D0D0",
    "bg": "#974200"
  },
  "mouse-drag-and-drop-region": {
    "bg": "#1E1E33"
  },
  "font-lock-property-use-face": {
    "fg": "#86e7d7"
  },
  "font-lock-property-name-face": {
    "fg": "#86e7d7"
  },
  "font-lock-number-face": {
    "fg": "#D85F00"
  },
  "font-lock-escape-face": {
    "fg": "#3679D8"
  },
  "font-lock-regexp-grouping-construct": {
    "fg": "#3679D8"
  },
  "font-lock-regexp-grouping-backslash": {
    "fg": "#3679D8"
  },
  "font-lock-regexp-face": {
    "fg": "#79D836"
  },
  "font-lock-preprocessor-face": {
    "fg": "#3679D8"
  },
  "font-lock-negation-char-face": {
    "fg": "#3679D8"
  },
  "font-lock-warning-face": {
    "fg": "#D85F00"
  },
  "font-lock-constant-face": {
    "fg": "#8041D8"
  },
  "font-lock-type-face": {
    "fg": "#3679D8"
  },
  "font-lock-variable-use-face": {
    "fg": "#86e7d7"
  },
  "font-lock-variable-name-face": {
    "fg": "#86e7d7"
  },
  "font-lock-function-call-face": {
    "fg": "#D8B941"
  },
  "font-lock-function-name-face": {
    "fg": "#D8B941"
  },
  "font-lock-builtin-face": {
    "fg": "#3679D8"
  },
  "font-lock-keyword-face": {
    "fg": "#D83441"
  },
  "font-lock-doc-markup-face": {
    "fg": "#8041D8"
  },
  "font-lock-doc-face": {
    "fg": "#9ae168"
  },
  "font-lock-string-face": {
    "fg": "#79D836"
  },
  "font-lock-comment-delimiter-face": {
    "fg": "#767676"
  },
  "font-lock-comment-face": {
    "fg": "#767676"
  },
  "completions-common-part": {
    "fg": "lightblue"
  },
  "completions-highlight": {
    "fg": "#0F1019",
    "bg": "#D85F00"
  },
  "completions-annotations": {
    "fg": "#767676"
  },
  "completions-group-separator": {
    "fg": "#767676"
  },
  "completions-group-title": {
    "fg": "#767676"
  },
  "blink-matching-paren-offscreen": {
    "fg": "green"
  },
  "separator-line": {
    "bg": "#505050"
  },
  "next-error-message": {
    "fg": "#0F1019",
    "bg": "#D85F00"
  },
  "next-error": {
    "bg": "#1E1E33"
  },
  "abbrev-table-name": {
    "fg": "#D8B941"
  },
  "button": {
    "fg": "#D85F00"
  },
  "show-paren-mismatch": {
    "fg": "#0F1019",
    "bg": "#D83441"
  },
  "show-paren-match-expression": {
    "fg": "#D83441",
    "bg": "#0F1019"
  },
  "show-paren-match": {
    "fg": "#D83441",
    "bg": "#0F1019"
  },
  "tty-menu-selected-face": {
    "bg": "red"
  },
  "tty-menu-disabled-face": {
    "fg": "lightgray",
    "bg": "blue"
  },
  "tty-menu-enabled-face": {
    "fg": "yellow",
    "bg": "blue"
  },
  "read-multiple-choice-face": {
    "fg": "LightBlue",
    "bg": "grey19"
  },
  "success": {
    "fg": "#79D836"
  },
  "warning": {
    "fg": "#D85F00"
  },
  "error": {
    "fg": "#D83441"
  },
  "help-key-binding": {
    "fg": "LightBlue",
    "bg": "grey19"
  },
  "tab-line": {
    "fg": "#040408",
    "bg": "#040408"
  },
  "tab-bar": {
    "fg": "#040408",
    "bg": "#040408"
  },
  "tool-bar": {
    "fg": "black",
    "bg": "grey75"
  },
  "cursor": {
    "bg": "#D85F00"
  },
  "fringe": {
    "fg": "#585C6C",
    "bg": "#0D0E16"
  },
  "minibuffer-prompt": {
    "fg": "#D85F00"
  },
  "internal-border": {
    "bg": "#B2B2B2"
  },
  "window-divider-last-pixel": {
    "fg": "#0F1019",
    "bg": "#0F1019"
  },
  "window-divider-first-pixel": {
    "fg": "#0F1019",
    "bg": "#0F1019"
  },
  "window-divider": {
    "fg": "#0F1019",
    "bg": "#0F1019"
  },
  "vertical-border": {
    "fg": "#0F1019",
    "bg": "#0F1019"
  },
  "header-line-inactive": {
    "bg": "#464A56"
  },
  "header-line-active": {
    "bg": "#464A56"
  },
  "header-line-highlight": {
    "fg": "#0F1019",
    "bg": "#D85F00"
  },
  "header-line": {
    "bg": "#464A56"
  },
  "mode-line-emphasis": {
    "fg": "#D85F00"
  },
  "mode-line-highlight": {
    "fg": "#0F1019",
    "bg": "#D85F00"
  },
  "mode-line-inactive": {
    "fg": "#B2B2B2",
    "bg": "#030306"
  },
  "mode-line-active": {
    "bg": "#464A56"
  },
  "mode-line": {
    "bg": "#464A56"
  },
  "nobreak-hyphen": {
    "fg": "cyan"
  },
  "nobreak-space": {
    "fg": "#36D8BD"
  },
  "homoglyph": {
    "fg": "cyan"
  },
  "escape-glyph": {
    "fg": "#36D8BD"
  },
  "fill-column-indicator": {
    "fg": "#767676"
  },
  "line-number-minor-tick": {
    "bg": "grey55"
  },
  "line-number-major-tick": {
    "bg": "grey75"
  },
  "line-number-current-line": {
    "fg": "#D85F00",
    "bg": "#040408"
  },
  "line-number": {
    "fg": "#585C6C",
    "bg": "#0D0E16"
  },
  "trailing-whitespace": {
    "bg": "#D83441"
  },
  "secondary-selection": {
    "bg": "#767676"
  },
  "region": {
    "bg": "#1E1E33"
  },
  "highlight": {
    "fg": "#0F1019",
    "bg": "#D85F00"
  },
  "link-visited": {
    "fg": "violet"
  },
  "link": {
    "fg": "#D85F00"
  },
  "shadow": {
    "fg": "#767676"
  },
  "default": {
    "fg": "#CEDBE5",
    "bg": "#0D0E16"
  }
}